[
    {
        "ID": 19724,
        "day": 1,
        "ji": "嫁娶、进人口、安葬、出行、赴任、入宅、移徙、入殓、开渠",
        "month": 1,
        "year": 1955,
        "yi": "祭祀、祈福、求嗣、开光、拆卸、修造、动土、上梁、安床、置产、栽种、破土"
    },
    {
        "ID": 19725,
        "day": 2,
        "ji": "移徙、入宅、嫁娶、祈福、开光、掘井",
        "month": 1,
        "year": 1955,
        "yi": "沐浴、冠笄、补垣、塞穴、合帐、裁衣、修造、作梁、开柱眼、安碓磑、筑堤、作厕、断蚁"
    },
    {
        "ID": 19726,
        "day": 3,
        "ji": "斋醮、入宅、修造、动土、破土",
        "month": 1,
        "year": 1955,
        "yi": "交易、进人口、祭祀、沐浴、捕捉、入殓、除服、成服、安葬、谢土、启攒、修坟"
    },
    {
        "ID": 19727,
        "day": 4,
        "ji": "斋醮、伐木、作梁、安葬、行丧",
        "month": 1,
        "year": 1955,
        "yi": "嫁娶、纳采、订盟、造车器、祭祀、祈福、造庙、安香、出火、出行、归宁、入学、入宅、交易、立券、求医、治病、修造、动土、竖柱、上梁、造屋、起基、安门"
    },
    {
        "ID": 19728,
        "day": 5,
        "ji": "嫁娶、动土、破土、祈福、出火、入宅",
        "month": 1,
        "year": 1955,
        "yi": "纳采、订盟、开市、交易、立券、出行、会亲友、安机械、竖柱、上梁、平治道涂、伐木、拆卸、造屋、起基、安床、安门、解除、安葬、启攒、除服、成服、修坟、立碑、移柩、入殓"
    },
    {
        "ID": 19729,
        "day": 6,
        "ji": "作灶、掘井、谢土、入宅",
        "month": 1,
        "year": 1955,
        "yi": "出行、嫁娶、订盟、纳采、入殓、安床、启攒、安葬、祭祀、裁衣、会亲友、进人口"
    },
    {
        "ID": 19730,
        "day": 7,
        "ji": "嫁娶、移徙、入宅、开光",
        "month": 1,
        "year": 1955,
        "yi": "修饰垣墙、平治道涂、入殓、移柩、余事勿取"
    },
    {
        "ID": 19731,
        "day": 8,
        "ji": "出行、治病、安葬、开市",
        "month": 1,
        "year": 1955,
        "yi": "会亲友、纳采、进人口、修造、动土、竖柱、上梁、祭祀、开光、塑绘、祈福、斋醮、嫁娶、安床、移徙、入宅、安香、纳畜"
    },
    {
        "ID": 19732,
        "day": 9,
        "ji": "造屋、开市、作灶、入宅",
        "month": 1,
        "year": 1955,
        "yi": "祭祀、会亲友、出行、订盟、纳采、沐浴、修造、动土、祈福、斋醮、嫁娶、拆卸、安床、入殓、移柩、安葬、谢土、赴任、裁衣、竖柱、上梁、伐木、捕捉、栽种、破土、安门"
    },
    {
        "ID": 19733,
        "day": 10,
        "ji": "诸事不宜",
        "month": 1,
        "year": 1955,
        "yi": "解除、破屋、坏垣、余事勿取"
    },
    {
        "ID": 19734,
        "day": 11,
        "ji": "入宅、安床",
        "month": 1,
        "year": 1955,
        "yi": "塑绘、开光、出行、订盟、纳采、除服、成服、嫁娶、纳婿、入殓、移柩、启攒、安葬、立碑"
    },
    {
        "ID": 19735,
        "day": 12,
        "ji": "破土、伐木",
        "month": 1,
        "year": 1955,
        "yi": "入殓、除服、成服、移柩、启攒、安葬、立碑、余事勿取"
    },
    {
        "ID": 19736,
        "day": 13,
        "ji": "开仓、造屋、安葬、安床",
        "month": 1,
        "year": 1955,
        "yi": "祭祀、祈福、斋醮、塑绘、开光、除服、成服、入殓、作灶、嫁娶、捕捉、畋猎、纳财"
    },
    {
        "ID": 19737,
        "day": 14,
        "ji": "栽种、嫁娶、入殓、安葬",
        "month": 1,
        "year": 1955,
        "yi": "祭祀、出行、沐浴、裁衣、祈福、斋醮、订盟、纳采、嫁娶、安机械、开市、立券、安碓磑、纳畜"
    },
    {
        "ID": 19738,
        "day": 15,
        "ji": "作灶、掘井、嫁娶、入宅",
        "month": 1,
        "year": 1955,
        "yi": "祭祀、祈福、斋醮、沐浴、安床、安机械、造车器、入殓、移柩、启攒、安葬、立碑、合帐、经络、交易"
    },
    {
        "ID": 19739,
        "day": 16,
        "ji": "余事勿取",
        "month": 1,
        "year": 1955,
        "yi": "解除、扫舍、祭祀、教牛马、余事勿取"
    },
    {
        "ID": 19740,
        "day": 17,
        "ji": "嫁娶、祭祀、出行、置产",
        "month": 1,
        "year": 1955,
        "yi": "开市、交易、立券、挂匾、开光、解除、伐木、作梁、出火、入宅、移徙、安床、拆卸、动土、上梁、栽种、纳畜、安葬"
    },
    {
        "ID": 19741,
        "day": 18,
        "ji": "修造、上梁、入宅、祈福、探病、掘井、动土、安门、安葬、作灶",
        "month": 1,
        "year": 1955,
        "yi": "开市、交易、立券、纳财、开池、补垣、嫁娶、纳采、纳畜、取渔、安床"
    },
    {
        "ID": 19742,
        "day": 19,
        "ji": "余事勿取",
        "month": 1,
        "year": 1955,
        "yi": "祭祀、解除、修饰垣墙、平治道涂、余事勿取"
    },
    {
        "ID": 19743,
        "day": 20,
        "ji": "掘井、安葬、栽种、出行、作灶、开市、入宅、安门",
        "month": 1,
        "year": 1955,
        "yi": "嫁娶、祭祀、祈福、求嗣、动土、会亲友、起基、造仓、纳畜、牧养、作厕、进人口"
    },
    {
        "ID": 19744,
        "day": 21,
        "ji": "掘井、安葬、栽种、出行、作灶、开市、入宅、安门",
        "month": 1,
        "year": 1955,
        "yi": "嫁娶、祭祀、祈福、求嗣、开光、入宅、移徙、安床、修造、动土、进人口"
    },
    {
        "ID": 19745,
        "day": 22,
        "ji": "诸事不宜",
        "month": 1,
        "year": 1955,
        "yi": "破屋、坏垣、余事勿取"
    },
    {
        "ID": 19746,
        "day": 23,
        "ji": "安床、伐木、祈福、纳畜",
        "month": 1,
        "year": 1955,
        "yi": "嫁娶、开市、交易、立券、开光、出行、出火、拆卸、修造、入宅、移徙、动土、破土、移柩、安葬、启攒、除服、成服"
    },
    {
        "ID": 19747,
        "day": 24,
        "ji": "余事勿取",
        "month": 1,
        "year": 1955,
        "yi": "祭祀、入殓、破土、除服、成服、启攒、安葬、修坟、立碑、余事勿取"
    },
    {
        "ID": 19748,
        "day": 25,
        "ji": "诸事不宜",
        "month": 1,
        "year": 1955,
        "yi": "祭祀、解除、余事勿取"
    },
    {
        "ID": 19749,
        "day": 26,
        "ji": "嫁娶、栽种、安葬、理发、造庙、作灶、入殓、行丧、造桥",
        "month": 1,
        "year": 1955,
        "yi": "开市、交易、立券、纳财、纳畜、造畜椆栖、入宅、移徙、安床、开光、祈福、求嗣、动土"
    },
    {
        "ID": 19750,
        "day": 27,
        "ji": "置产、嫁娶、出行、开光、栽种、动土、破土、入宅、治病",
        "month": 1,
        "year": 1955,
        "yi": "安床、裁衣、交易、立券、入殓、移柩、安葬、除服、成服"
    },
    {
        "ID": 19751,
        "day": 28,
        "ji": "嫁娶、动土、开池、安葬",
        "month": 1,
        "year": 1955,
        "yi": "祭祀、解除、造畜椆栖、教牛马、针灸、余事勿取"
    },
    {
        "ID": 19752,
        "day": 29,
        "ji": "入宅、安门、祭祀、谢土",
        "month": 1,
        "year": 1955,
        "yi": "沐浴、塑绘、开光、纳采、订盟、开市、交易、立券、纳财、起基、动土、定磉、放水、安葬、破土、启攒、修坟、立碑、移柩"
    },
    {
        "ID": 19753,
        "day": 30,
        "ji": "掘井、祈福、谢土、动土、入宅、上梁、修造、作灶",
        "month": 1,
        "year": 1955,
        "yi": "嫁娶、出行、理发、安床、启攒、安葬、修坟、开市、交易、立券、纳财、开池、牧养"
    },
    {
        "ID": 19754,
        "day": 31,
        "ji": "移徙、入宅、掘井、造庙、栽种、针灸、治病、开池",
        "month": 1,
        "year": 1955,
        "yi": "解除、平治道涂、余事勿取"
    },
    {
        "ID": 19755,
        "day": 1,
        "ji": "开市、行丧、栽种、出行、出货财、安葬、置产、词讼、治病",
        "month": 2,
        "year": 1955,
        "yi": "嫁娶、祭祀、开光、伐木、出火、拆卸、入宅、移徙、修造、动土、上梁、安床、纳畜"
    },
    {
        "ID": 19756,
        "day": 2,
        "ji": "伐木、开市、交易、上梁、作灶、安门、造屋",
        "month": 2,
        "year": 1955,
        "yi": "嫁娶、纳采、订盟、入宅、移徙、安床、祭祀、祈福、开光、出行、解除、出火、拆卸、动土、纳畜、谢土、安葬、破土"
    },
    {
        "ID": 19757,
        "day": 3,
        "ji": "开市、动土、破土",
        "month": 2,
        "year": 1955,
        "yi": "祭祀、破屋、坏垣、解除、余事勿取"
    },
    {
        "ID": 19758,
        "day": 4,
        "ji": "诸事不宜",
        "month": 2,
        "year": 1955,
        "yi": "求医、破屋"
    },
    {
        "ID": 19759,
        "day": 5,
        "ji": "作灶、安床",
        "month": 2,
        "year": 1955,
        "yi": "祈福、求嗣、斋醮、塑绘、开光、订盟、纳采、嫁娶、动土、入宅、安香、移柩、安葬、谢土、出行、沐浴、修造、竖柱、上梁、纳财、破土、解除、安门、放水"
    },
    {
        "ID": 19760,
        "day": 6,
        "ji": "嫁娶、上梁、入宅、作灶",
        "month": 2,
        "year": 1955,
        "yi": "取渔、入殓、除服、成服、移柩、破土、安葬、立碑"
    },
    {
        "ID": 19761,
        "day": 7,
        "ji": "安葬、作灶、伐木、作梁",
        "month": 2,
        "year": 1955,
        "yi": "祭祀、求嗣、沐浴、酬神、订盟、纳采、裁衣、合帐、冠笄、安机械、安床、造仓、开池、经络、纳财、开市、立券、交易、结网、取渔、纳畜、捕捉"
    },
    {
        "ID": 19762,
        "day": 8,
        "ji": "入殓、安葬、作灶、入宅",
        "month": 2,
        "year": 1955,
        "yi": "祭祀、沐浴、祈福、求嗣、斋醮、订盟、纳采、裁衣、冠笄、开市、立券、交易、纳财、沐浴、除服、谢土、出行、移柩"
    },
    {
        "ID": 19763,
        "day": 9,
        "ji": "开光、掘井、针灸、出行、嫁娶、入宅、移徙、作灶、动土",
        "month": 2,
        "year": 1955,
        "yi": "祭祀、祈福、求嗣、入殓、启攒、安葬、移柩"
    },
    {
        "ID": 19764,
        "day": 10,
        "ji": "嫁娶、出行、动土、开渠、入宅、祭祀、掘井",
        "month": 2,
        "year": 1955,
        "yi": "安床、解除、裁衣、竖柱、上梁、交易、立券、纳财、纳畜、牧养、入殓、移柩、安葬、启攒"
    },
    {
        "ID": 19765,
        "day": 11,
        "ji": "掘井、词讼",
        "month": 2,
        "year": 1955,
        "yi": "嫁娶、安床、开光、出行、祭祀、动土、出火、解除、会亲友、开市、交易、立券、挂匾、入宅、移徙、拆卸、破土、启攒、安葬"
    },
    {
        "ID": 19766,
        "day": 12,
        "ji": "入宅、移徙、出火、分居、安香、作灶、开市、交易、立券、安葬、动土、伐木",
        "month": 2,
        "year": 1955,
        "yi": "嫁娶、开光、求嗣、会亲友、安床、牧养、塑绘、针灸"
    },
    {
        "ID": 19767,
        "day": 13,
        "ji": "栽种、出行、祈福、行丧、纳畜、安葬、安门、伐木、作梁、牧养",
        "month": 2,
        "year": 1955,
        "yi": "作灶、解除、平治道涂"
    },
    {
        "ID": 19768,
        "day": 14,
        "ji": "诸事不宜",
        "month": 2,
        "year": 1955,
        "yi": "解除、沐浴"
    },
    {
        "ID": 19769,
        "day": 15,
        "ji": "开市、立券、理发、作灶",
        "month": 2,
        "year": 1955,
        "yi": "嫁娶、祭祀、祈福、出行、解除、出火、拆卸、动土、入宅、移徙、安床、上梁、栽种、纳畜、破土、启攒、安葬"
    },
    {
        "ID": 19770,
        "day": 16,
        "ji": "余事勿取",
        "month": 2,
        "year": 1955,
        "yi": "祭祀、解除、治病、破屋、坏垣、扫舍"
    },
    {
        "ID": 19771,
        "day": 17,
        "ji": "嫁娶、作灶、安床",
        "month": 2,
        "year": 1955,
        "yi": "祭祀、祈福、求嗣、开光、出火、出行、拆卸、修造、动土、入宅、移徙、上梁、挂匾、开池、入殓、安葬、破土、启攒"
    },
    {
        "ID": 19772,
        "day": 18,
        "ji": "诸事不宜",
        "month": 2,
        "year": 1955,
        "yi": "结网、入殓、除服、成服、移柩、安葬、破土"
    },
    {
        "ID": 19773,
        "day": 19,
        "ji": "嫁娶、安葬、破土、作梁、纳畜、牧养、行丧、作灶",
        "month": 2,
        "year": 1955,
        "yi": "移徙、祭祀、开光、祈福、出行、解除、进人口、雇庸、安床、动土、起基、上梁、安门、解除"
    },
    {
        "ID": 19774,
        "day": 20,
        "ji": "入宅、作灶、伐木、安葬、出火、出行、纳畜",
        "month": 2,
        "year": 1955,
        "yi": "嫁娶、开光、祈福、求嗣、解除、动土、安床、栽种、开池、掘井、祭祀、破土、启攒"
    },
    {
        "ID": 19775,
        "day": 21,
        "ji": "词讼、出火、入宅",
        "month": 2,
        "year": 1955,
        "yi": "祭祀、合帐、裁衣、经络、伐木、作梁、安床、作灶、入殓、安葬、启攒、移柩"
    },
    {
        "ID": 19776,
        "day": 22,
        "ji": "诸事不宜",
        "month": 2,
        "year": 1955,
        "yi": "裁衣、伐木、作梁、纳财、交易、立券"
    },
    {
        "ID": 19777,
        "day": 23,
        "ji": "诸事不宜",
        "month": 2,
        "year": 1955,
        "yi": "嫁娶、祭祀、祈福、求嗣、开光、出行、出火、拆卸、动土、上梁、进人口、入宅、移徙、安床、开市、交易、立券、挂匾、入殓、破土、安葬、启攒、除服、成服"
    },
    {
        "ID": 19778,
        "day": 24,
        "ji": "入宅、作灶、治病、安葬、移徙",
        "month": 2,
        "year": 1955,
        "yi": "嫁娶、冠笄、纳采、出行、会亲友、上梁、安机械、安床、牧养、畋猎、祭祀、祈福、开光、修造、安门、造屋、起基"
    },
    {
        "ID": 19779,
        "day": 25,
        "ji": "诸事不宜",
        "month": 2,
        "year": 1955,
        "yi": "修饰垣墙、平治道涂、祭祀、余事勿取"
    },
    {
        "ID": 19780,
        "day": 26,
        "ji": "开光、造屋、动土、作灶、栽种",
        "month": 2,
        "year": 1955,
        "yi": "造车器、纳采、订盟、祭祀、祈福、求嗣、移徙、出行、开市、出火、入宅、立券、交易、入宅、安门、安床、安葬、谢土"
    },
    {
        "ID": 19781,
        "day": 27,
        "ji": "开市、作灶、安床、入宅、上梁、裁衣",
        "month": 2,
        "year": 1955,
        "yi": "动土、入殓、嫁娶、移柩、安葬、破土"
    },
    {
        "ID": 19782,
        "day": 28,
        "ji": "开市、嫁娶",
        "month": 2,
        "year": 1955,
        "yi": "求医、治病、破屋、坏垣、余事勿取"
    },
    {
        "ID": 19783,
        "day": 1,
        "ji": "开市、嫁娶、安床、会亲友、入宅、作灶、上梁",
        "month": 3,
        "year": 1955,
        "yi": "祭祀、斋醮、沐浴、开生坟、除服、成服、移柩、入殓、破土、安葬、合寿木"
    },
    {
        "ID": 19784,
        "day": 2,
        "ji": "嫁娶、入宅",
        "month": 3,
        "year": 1955,
        "yi": "祭祀、塞穴、结网、破土、谢土、安葬、移柩、除服、成服、余事勿取"
    },
    {
        "ID": 19785,
        "day": 3,
        "ji": "嫁娶、词讼、行丧、安葬、牧养、伐木、作梁、开市、纳畜、造畜椆栖",
        "month": 3,
        "year": 1955,
        "yi": "祭祀、沐浴、理发、作灶、结网、栽种"
    },
    {
        "ID": 19786,
        "day": 4,
        "ji": "入宅、安葬、伐木、作梁、纳畜、造畜椆栖、作灶",
        "month": 3,
        "year": 1955,
        "yi": "嫁娶、祭祀、开光、祈福、求嗣、出行、开市、交易、立券、动土、纳财、掘井、会亲友"
    },
    {
        "ID": 19787,
        "day": 5,
        "ji": "栽种、开光、出行、针灸、嫁娶、入宅、动土、破土",
        "month": 3,
        "year": 1955,
        "yi": "祭祀、祈福、求嗣、纳畜、入殓、启攒、谢土、除服、成服"
    },
    {
        "ID": 19788,
        "day": 6,
        "ji": "作灶、开光、嫁娶、开市、入宅",
        "month": 3,
        "year": 1955,
        "yi": "订盟、纳采、冠笄、拆卸、修造、动土、安床、入殓、除服、成服、移柩、安葬、破土、启攒、造仓"
    },
    {
        "ID": 19789,
        "day": 7,
        "ji": "作灶、掘井、动土、栽种",
        "month": 3,
        "year": 1955,
        "yi": "祈福、开光、塑绘、酬神、订盟、纳采、裁衣、安床、开市、立券、入殓、除服、成服、移柩、启攒、安葬、立碑、赴任、会亲友、出行、交易、竖柱"
    },
    {
        "ID": 19790,
        "day": 8,
        "ji": "栽种、作灶、安葬、嫁娶",
        "month": 3,
        "year": 1955,
        "yi": "祭祀、扫舍、塞穴"
    },
    {
        "ID": 19791,
        "day": 9,
        "ji": "出行、嫁娶、入宅、安葬",
        "month": 3,
        "year": 1955,
        "yi": "开光、塑绘、裁衣、冠笄、伐木、拆卸、竖柱、上梁、开仓、会亲友、安机械、造仓、造屋、交易、解除、开市、立券、纳财"
    },
    {
        "ID": 19792,
        "day": 10,
        "ji": "造屋、作灶、治病、探病",
        "month": 3,
        "year": 1955,
        "yi": "冠笄、入殓、除服、成服、移柩、平治道涂、修饰垣墙"
    },
    {
        "ID": 19793,
        "day": 11,
        "ji": "栽种、伐木",
        "month": 3,
        "year": 1955,
        "yi": "祭祀、嫁娶、祈福、纳采、裁衣、合帐、安床、入宅、安香、入殓、移柩、安葬、谢土、修造、安碓磑、求嗣、会亲友、挂匾、交易、立券、纳财、造仓、放水"
    },
    {
        "ID": 19794,
        "day": 12,
        "ji": "安床、开市、立券、作灶",
        "month": 3,
        "year": 1955,
        "yi": "祭祀、祈福、斋醮、订盟、纳采、裁衣、合帐、拆卸、修造、动土、上梁、起基、移柩、安葬、谢土、沐浴、扫舍、开柱眼、伐木、出火"
    },
    {
        "ID": 19795,
        "day": 13,
        "ji": "诸事不宜",
        "month": 3,
        "year": 1955,
        "yi": "破屋、坏垣、求医、治病"
    },
    {
        "ID": 19796,
        "day": 14,
        "ji": "开光、出货财",
        "month": 3,
        "year": 1955,
        "yi": "祭祀、动土、上梁、订盟、纳采、嫁娶、安机械、拆卸、安床、入宅、安香、入殓、移柩、破土、安葬、立碑、谢土、赴任、出行、移徙、祈福、求嗣、解除、造仓、进人口"
    },
    {
        "ID": 19797,
        "day": 15,
        "ji": "嫁娶、栽种、伐木、安葬",
        "month": 3,
        "year": 1955,
        "yi": "祭祀、开光、塑绘、纳采、裁衣、拆卸、安床、起基、动土、竖柱、上梁、移徙、入宅、安香、开市、立券、挂匾、沐浴、出行、求嗣、安门"
    },
    {
        "ID": 19798,
        "day": 16,
        "ji": "作灶、开市、安葬、作梁",
        "month": 3,
        "year": 1955,
        "yi": "裁衣、合帐、冠笄、嫁娶、纳婿、安床、入殓、纳财"
    },
    {
        "ID": 19799,
        "day": 17,
        "ji": "作灶、安葬、开市、造屋",
        "month": 3,
        "year": 1955,
        "yi": "祭祀、订盟、纳采、修造、动土、祈福、塑绘、斋醮、沐浴、拆卸、起基、入宅、安香、造庙、移柩、谢土、除服、成服、入学、习艺、出行、竖柱、上梁、掘井、求嗣、解除、伐木"
    },
    {
        "ID": 19800,
        "day": 18,
        "ji": "祭祀、开光、嫁娶、入宅",
        "month": 3,
        "year": 1955,
        "yi": "订盟、纳采、裁衣、合帐、冠笄、安机械、拆卸、安床、入殓、除服、成服、移柩、破土、启攒、安葬、修坟、立碑、经络、交易、立券、纳财、筑堤、造仓、补垣、塞穴、纳畜、伐木、架马"
    },
    {
        "ID": 19801,
        "day": 19,
        "ji": "掘井、动土、作灶、栽种",
        "month": 3,
        "year": 1955,
        "yi": "祭祀、出行、嫁娶、冠笄、安床、入殓、移柩、安葬"
    },
    {
        "ID": 19802,
        "day": 20,
        "ji": "安门、作灶、安葬、嫁娶",
        "month": 3,
        "year": 1955,
        "yi": "塞穴、诸事不宜"
    },
    {
        "ID": 19803,
        "day": 21,
        "ji": "出行、斋醮、安葬、嫁娶",
        "month": 3,
        "year": 1955,
        "yi": "开光、塑绘、求嗣、纳采、裁衣、合帐、冠笄、安机械、作梁、开柱眼、安门、安床、造仓、祭祀、会亲友、祈福、经络、纳财、开市、立券、交易、入学、求嗣、理发、架马"
    },
    {
        "ID": 19804,
        "day": 22,
        "ji": "栽种、造屋、作灶、入宅",
        "month": 3,
        "year": 1955,
        "yi": "祭祀、嫁娶、纳婿、安葬"
    },
    {
        "ID": 19805,
        "day": 23,
        "ji": "伐木、作梁",
        "month": 3,
        "year": 1955,
        "yi": "祭祀、会亲友、订盟、裁衣、合帐、安机械、拆卸、上梁、安门、入殓、除服、成服、移柩、启攒、安葬、立碑、开光、塑绘、入学、出行、起基、定磉、放水、移徙、入宅、竖柱、立券、经络"
    },
    {
        "ID": 19806,
        "day": 24,
        "ji": "入宅、安门",
        "month": 3,
        "year": 1955,
        "yi": "祭祀、开光、塑绘、祈福、斋醮、裁衣、合帐、冠笄、嫁娶、拆卸、动土、移徙、入宅、入殓、移柩、安葬、谢土、求嗣、入学、理发、伐木、架马、作梁、出火、修造、起基、定磉、放水、赴任"
    },
    {
        "ID": 19807,
        "day": 25,
        "ji": "诸事不宜",
        "month": 3,
        "year": 1955,
        "yi": "祭祀、治病、破屋、坏垣、余事勿取"
    },
    {
        "ID": 19808,
        "day": 26,
        "ji": "开光、作灶、斋醮、安葬",
        "month": 3,
        "year": 1955,
        "yi": "嫁娶、祭祀、出行、冠笄、立券、交易、进人口、开市、移徙、修造、动土、安床、入殓、移柩、破土"
    },
    {
        "ID": 19809,
        "day": 27,
        "ji": "嫁娶、行丧、架马、作梁、理发、牧养、安葬、纳畜、伐木",
        "month": 3,
        "year": 1955,
        "yi": "开市、立券、交易、挂匾、祭祀、祈福、开光、入宅、移徙、安床、拆卸、动土、上梁、进人口"
    },
    {
        "ID": 19810,
        "day": 28,
        "ji": "置产、伐木、纳畜、造畜椆栖、安葬、破土、作梁、作灶、开生坟",
        "month": 3,
        "year": 1955,
        "yi": "理发、冠笄、嫁娶、进人口"
    },
    {
        "ID": 19811,
        "day": 29,
        "ji": "合帐、开市、安葬、入殓",
        "month": 3,
        "year": 1955,
        "yi": "嫁娶、祭祀、开光、祈福、求嗣、出火、入宅、移徙、安床、拆卸、动土、破土、谢土"
    },
    {
        "ID": 19812,
        "day": 30,
        "ji": "嫁娶、祭祀、开光、出行、出火、移徙、入宅、安门",
        "month": 3,
        "year": 1955,
        "yi": "安床、伐木、拆卸、修造、动土、上梁、立券、交易、栽种、纳畜、牧养、入殓、安葬"
    },
    {
        "ID": 19813,
        "day": 31,
        "ji": "祈福、动土、移徙、入宅",
        "month": 3,
        "year": 1955,
        "yi": "祭祀、祈福、求嗣、斋醮、嫁娶、冠笄、出行、开市、交易、会亲友、教牛马、除服、成服、启攒、安葬、移柩"
    },
    {
        "ID": 19814,
        "day": 1,
        "ji": "嫁娶、作灶、掘井、安葬",
        "month": 4,
        "year": 1955,
        "yi": "塞穴、整手足甲、解除、捕捉、畋猎、结网、余事勿取、诸事不宜"
    },
    {
        "ID": 19815,
        "day": 2,
        "ji": "动土、破土、安葬、行丧、赴任、出行、嫁娶、入宅、移徙、谢土、词讼",
        "month": 4,
        "year": 1955,
        "yi": "纳财、开市、立券、交易、开光、安床、上梁、造屋、修造、起基"
    },
    {
        "ID": 19816,
        "day": 3,
        "ji": "开仓、出货财、造屋、作灶、开市、交易、立券、栽种",
        "month": 4,
        "year": 1955,
        "yi": "祭祀、祈福、嫁娶、冠笄、修饰垣墙、置产、平治道涂"
    },
    {
        "ID": 19817,
        "day": 4,
        "ji": "动土、伐木、安葬、行丧",
        "month": 4,
        "year": 1955,
        "yi": "嫁娶、祭祀、开光、祈福、求嗣、出行、出火、进人口、入宅、移徙、安床、拆卸、修造、安门、挂匾、纳财、扫舍"
    },
    {
        "ID": 19818,
        "day": 5,
        "ji": "嫁娶、移徙、入宅",
        "month": 4,
        "year": 1955,
        "yi": "祭祀、斋醮、开市、动土、入殓、破土、安葬"
    },
    {
        "ID": 19819,
        "day": 6,
        "ji": "开市、动土、破土",
        "month": 4,
        "year": 1955,
        "yi": "嫁娶、纳采、祭祀、祈福、出行、移徙、求医"
    },
    {
        "ID": 19820,
        "day": 7,
        "ji": "诸事不宜",
        "month": 4,
        "year": 1955,
        "yi": "祭祀、求医、治病、解除、余事勿取"
    },
    {
        "ID": 19821,
        "day": 8,
        "ji": "嫁娶、入宅、安葬",
        "month": 4,
        "year": 1955,
        "yi": "沐浴、结网、取渔"
    },
    {
        "ID": 19822,
        "day": 9,
        "ji": "诸事不宜",
        "month": 4,
        "year": 1955
    },
    {
        "ID": 19823,
        "day": 10,
        "ji": "诸事不宜",
        "month": 4,
        "year": 1955,
        "yi": "解除、坏垣、余事勿取"
    },
    {
        "ID": 19824,
        "day": 11,
        "ji": "祈福、入殓、祭祀、作灶、安葬、探病",
        "month": 4,
        "year": 1955,
        "yi": "嫁娶、开光、出行、出火、拆卸、进人口、开市、立券、交易、挂匾、入宅、移徙、安床、栽种"
    },
    {
        "ID": 19825,
        "day": 12,
        "ji": "词讼、开光、开市",
        "month": 4,
        "year": 1955,
        "yi": "嫁娶、出行、合帐、冠笄、安床、除服、成服、作灶、交易、立券、入殓、移柩、破土、安葬"
    },
    {
        "ID": 19826,
        "day": 13,
        "ji": "诸事不宜",
        "month": 4,
        "year": 1955,
        "yi": "出行、修饰垣墙、造畜椆栖、教牛马、余事勿取"
    },
    {
        "ID": 19827,
        "day": 14,
        "ji": "嫁娶、纳财、安葬、出行、开市、立券、作灶、栽种",
        "month": 4,
        "year": 1955,
        "yi": "祭祀、祈福、开光、求嗣、解除、伐木、出火、入宅、移徙、安床、拆卸、修造、动土、造畜椆栖"
    },
    {
        "ID": 19828,
        "day": 15,
        "ji": "谢土、祈福、上梁、作灶、斋醮、修造、入宅、安门",
        "month": 4,
        "year": 1955,
        "yi": "纳采、嫁娶、开光、出行、理发、会亲友、开市、安床、栽种、牧养、入殓、移柩、启攒"
    },
    {
        "ID": 19829,
        "day": 16,
        "ji": "诸事不宜",
        "month": 4,
        "year": 1955,
        "yi": "祭祀、平治道涂、解除、修饰垣墙、余事勿取"
    },
    {
        "ID": 19830,
        "day": 17,
        "ji": "进人口、出行、嫁娶、置产、安床、赴任、安葬、作灶",
        "month": 4,
        "year": 1955,
        "yi": "祭祀、祈福、开光、解除、动土、纳财、交易、纳畜、扫舍"
    },
    {
        "ID": 19831,
        "day": 18,
        "ji": "动土、破土、纳财、掘井、挂匾、开市、伐木、交易",
        "month": 4,
        "year": 1955,
        "yi": "祭祀、祈福、求嗣、开光、解除、出火、拆卸、入宅、安床、修造、安门、纳畜、启攒、安葬"
    },
    {
        "ID": 19832,
        "day": 19,
        "ji": "诸事不宜",
        "month": 4,
        "year": 1955,
        "yi": "祭祀、解除、破屋、坏垣、余事勿取"
    },
    {
        "ID": 19833,
        "day": 20,
        "ji": "诸事不宜",
        "month": 4,
        "year": 1955,
        "yi": "塞穴、扫舍、余事勿取"
    },
    {
        "ID": 19834,
        "day": 21,
        "month": 4,
        "year": 1955,
        "yi": "祭祀、祈福、求嗣、开光、解除、纳采、冠笄、出火、拆卸、进人口、安床、动土、上梁、造庙、掘井、开池、入殓、移柩、安葬、破土"
    },
    {
        "ID": 19835,
        "day": 22,
        "ji": "诸事不宜",
        "month": 4,
        "year": 1955,
        "yi": "解除、破屋、余事勿取"
    },
    {
        "ID": 19836,
        "day": 23,
        "ji": "祭祀、入殓、安葬、探病",
        "month": 4,
        "year": 1955,
        "yi": "嫁娶、祈福、求嗣、开光、出行、解除、拆卸、出火、开市、立券、交易、入宅、移徙、安床、动土、破土、谢土"
    },
    {
        "ID": 19837,
        "day": 24,
        "ji": "嫁娶、掘井、探病、开市、开光、栽种",
        "month": 4,
        "year": 1955,
        "yi": "祭祀、裁衣、冠笄、安床、交易、立券、开池、补垣、塞穴、入殓、破土、启攒、安葬、谢土、除服、成服"
    },
    {
        "ID": 19838,
        "day": 25,
        "ji": "开光、伐木、安葬、破土",
        "month": 4,
        "year": 1955,
        "yi": "祭祀、出行、教牛马、扫舍、余事勿取"
    },
    {
        "ID": 19839,
        "day": 26,
        "ji": "修坟、造桥、作灶、出行、安葬、造屋、入宅",
        "month": 4,
        "year": 1955,
        "yi": "祭祀、祈福、求嗣、开光、纳采、订盟、解除、栽种、纳畜、牧养、扫舍、进人口"
    },
    {
        "ID": 19840,
        "day": 27,
        "ji": "祈福、出火、置产、动土、破土、安葬、修造、上梁、置产、入宅",
        "month": 4,
        "year": 1955,
        "yi": "开光、出行、交易、塞穴、嫁娶、理发、开市、安床"
    },
    {
        "ID": 19841,
        "day": 28,
        "ji": "嫁娶、安床、治病",
        "month": 4,
        "year": 1955,
        "yi": "祭祀、作灶、畋猎、结网、修饰垣墙、平治道涂、余事勿取"
    },
    {
        "ID": 19842,
        "day": 29,
        "ji": "斋醮、开光、嫁娶、入宅、上梁",
        "month": 4,
        "year": 1955,
        "yi": "沐浴、祭祀、解除、安葬、破土、谢土、移柩、余事勿取"
    },
    {
        "ID": 19843,
        "day": 30,
        "ji": "动土、破土",
        "month": 4,
        "year": 1955,
        "yi": "祭祀、解除、入殓、移柩、启攒、安葬、整手足甲、捕捉、畋猎、取渔、除服、成服、扫舍、谢土、斋醮"
    },
    {
        "ID": 19844,
        "day": 1,
        "ji": "嫁娶、开市",
        "month": 5,
        "year": 1955,
        "yi": "祭祀、沐浴、解除、破屋、坏垣、求医、治病、余事勿取"
    },
    {
        "ID": 19845,
        "day": 2,
        "ji": "祈福、安葬",
        "month": 5,
        "year": 1955,
        "yi": "沐浴、塞穴、畋猎、结网、取渔、扫舍、余事勿取"
    },
    {
        "ID": 19846,
        "day": 3,
        "ji": "纳采、问名、订盟、嫁娶、入宅、开仓、出火、动土、破土、纳畜、伐木",
        "month": 5,
        "year": 1955,
        "yi": "开市、交易、立券、挂匾、祭祀、开光、祈福、求嗣、安床、解除、修造、安葬"
    },
    {
        "ID": 19847,
        "day": 4,
        "ji": "嫁娶、入宅",
        "month": 5,
        "year": 1955,
        "yi": "祭祀、修门、取渔、纳财、纳畜、余事勿取"
    },
    {
        "ID": 19848,
        "day": 5,
        "ji": "作灶、安葬、祭祀、入殓",
        "month": 5,
        "year": 1955,
        "yi": "安香、出火、纳采、订盟、嫁娶、开市、立券、交易、挂匾、开光、出行、解除、安床、栽种、置产、拆卸、修造、动土"
    },
    {
        "ID": 19849,
        "day": 6,
        "ji": "嫁娶、安葬",
        "month": 5,
        "year": 1955,
        "yi": "订盟、纳采、祭祀、动土、破土、交易、立券"
    },
    {
        "ID": 19850,
        "day": 7,
        "ji": "赴任、捕捉",
        "month": 5,
        "year": 1955,
        "yi": "嫁娶、裁衣、祭祀、出行、安床、作灶、移徙、入宅、破土、安葬"
    },
    {
        "ID": 19851,
        "day": 8,
        "ji": "诸事不宜",
        "month": 5,
        "year": 1955,
        "yi": "塞穴、结网、余事勿取"
    },
    {
        "ID": 19852,
        "day": 9,
        "ji": "移徙、入宅",
        "month": 5,
        "year": 1955,
        "yi": "嫁娶、订盟、纳采、出行、祭祀、祈福、斋醮、动土、上梁、破土、安葬"
    },
    {
        "ID": 19853,
        "day": 10,
        "ji": "开市、安葬",
        "month": 5,
        "year": 1955,
        "yi": "订盟、纳采、会亲友、安床、作灶、造畜椆栖"
    },
    {
        "ID": 19854,
        "day": 11,
        "ji": "诸事不宜",
        "month": 5,
        "year": 1955,
        "yi": "沐浴、平治道涂、扫舍、入殓、移柩、破土、启攒、安葬、余事勿取"
    },
    {
        "ID": 19855,
        "day": 12,
        "month": 5,
        "year": 1955,
        "yi": "嫁娶、祭祀、祈福、求嗣、开光、出行、出火、拆卸、动土、上梁、进人口、入宅、移徙、安床、安门、开市、交易、立券、挂匾、栽种、破土、安葬"
    },
    {
        "ID": 19856,
        "day": 13,
        "ji": "嫁娶、上梁、修造、拆卸、架马、入宅、伐木、动土、出火、开柱眼",
        "month": 5,
        "year": 1955,
        "yi": "祭祀、开光、出行、解除、塑绘、裁衣、入殓、移柩、破土、启攒、安葬、除服、成服"
    },
    {
        "ID": 19857,
        "day": 14,
        "ji": "诸事不宜",
        "month": 5,
        "year": 1955,
        "yi": "祭祀、解除、破屋、坏垣、余事勿取"
    },
    {
        "ID": 19858,
        "day": 15,
        "month": 5,
        "year": 1955,
        "yi": "嫁娶、祭祀、祈福、求嗣、开光、出行、拆卸、动土、上梁、出火、进人口、入宅、移徙、安床、栽种、纳畜、牧养、竖柱、安门、修造、解除、会亲友"
    },
    {
        "ID": 19859,
        "day": 16,
        "ji": "入宅、移徙、理发、出火、嫁娶、出行",
        "month": 5,
        "year": 1955,
        "yi": "开市、交易、立券、祭祀、祈福、开光、伐木、进人口、安床、拆卸、修造、动土、栽种、破土、移柩、安葬"
    },
    {
        "ID": 19860,
        "day": 17,
        "ji": "诸事不宜",
        "month": 5,
        "year": 1955,
        "yi": "结网、解除、余事勿取"
    },
    {
        "ID": 19861,
        "day": 18,
        "ji": "纳畜、入宅、移徙、安葬、探病、伐木、上梁、安门、入殓、动土",
        "month": 5,
        "year": 1955,
        "yi": "嫁娶、祭祀、祈福、求嗣、开光、开市、交易、立券、安床、出行、拆卸"
    },
    {
        "ID": 19862,
        "day": 19,
        "ji": "开光、掘井、开仓",
        "month": 5,
        "year": 1955,
        "yi": "嫁娶、祭祀、祈福、求嗣、出行、出火、拆卸、修造、动土、入宅、移徙、安床、作灶、塞穴、栽种、破土、安葬"
    },
    {
        "ID": 19863,
        "day": 20,
        "ji": "诸事不宜",
        "month": 5,
        "year": 1955,
        "yi": "解除、扫舍、余事勿取"
    },
    {
        "ID": 19864,
        "day": 21,
        "ji": "嫁娶、安床、探病、作灶",
        "month": 5,
        "year": 1955,
        "yi": "开市、交易、立券、挂匾、开光、出行、拆卸、进人口、入宅、移柩、动土、安门、上梁、栽种、破土、修坟、安葬"
    },
    {
        "ID": 19865,
        "day": 22,
        "ji": "塞穴、上梁、动土、伐木、安葬、词讼",
        "month": 5,
        "year": 1955,
        "yi": "进人口、会亲友"
    },
    {
        "ID": 19866,
        "day": 23,
        "ji": "嫁娶、移徙、伐木、作梁、安床、祭祀、祈福、造屋",
        "month": 5,
        "year": 1955,
        "yi": "沐浴、平治道涂、扫舍、入殓、破土、安葬、除服、成服"
    },
    {
        "ID": 19867,
        "day": 24,
        "month": 5,
        "year": 1955,
        "yi": "嫁娶、祭祀、祈福、求嗣、开光、出火、出行、拆卸、动土、解除、进人口、开市、交易、立券、挂匾、入宅、移徙、安床、安门、上梁、安葬、破土、谢土"
    },
    {
        "ID": 19868,
        "day": 25,
        "month": 5,
        "year": 1955,
        "yi": "祭祀、祈福、求嗣、开光、解除、合帐、冠笄、伐木、架马、作梁、修造、进人口、嫁娶、裁衣、合帐、安床、动土、起基、上梁、竖柱、放水、会亲友"
    },
    {
        "ID": 19869,
        "day": 26,
        "ji": "诸事不宜",
        "month": 5,
        "year": 1955,
        "yi": "破屋、坏垣、沐浴、解除、余事勿取"
    },
    {
        "ID": 19870,
        "day": 27,
        "ji": "开市、立券",
        "month": 5,
        "year": 1955,
        "yi": "纳采、订盟、嫁娶、造车器、祭祀、祈福、求嗣、开光、出火、拆卸、修造、动土、进人口、挂匾、入宅、移徙、安床、栽种、入殓、破土、安葬、除服、成服"
    },
    {
        "ID": 19871,
        "day": 28,
        "ji": "嫁娶、掘井、入宅、移徙、安葬",
        "month": 5,
        "year": 1955,
        "yi": "开市、交易、立券、祭祀、祈福、开光、动土、安床、出行、栽种、纳畜、牧养、竖柱、上梁、解除、破土"
    },
    {
        "ID": 19872,
        "day": 29,
        "ji": "祭祀、伐木、架马、安床、修造、动土、安葬、修坟、破土",
        "month": 5,
        "year": 1955,
        "yi": "解除、出行、纳采、冠笄、竖柱、上梁、移徙、作灶、进人口、入宅、纳畜、牧养"
    },
    {
        "ID": 19873,
        "day": 30,
        "ji": "入宅、移徙、修造、安门、伐木、入殓、安葬、造屋",
        "month": 5,
        "year": 1955,
        "yi": "祭祀、祈福、求嗣、开光、出行、开市、交易、立券、栽种、安床、纳畜、移徙、起基、动土、定磉、造仓、置产、破土、启攒、修坟"
    },
    {
        "ID": 19874,
        "day": 31,
        "ji": "安床、开渠、上梁、修造、开市、开光、入宅、移徙、安床",
        "month": 5,
        "year": 1955,
        "yi": "嫁娶、交易、立券、作厕、补垣、塞穴、畋猎、取渔、开生坟"
    },
    {
        "ID": 19875,
        "day": 1,
        "ji": "嫁娶、安葬、入宅、出行、动土、词讼",
        "month": 6,
        "year": 1955,
        "yi": "塞穴、断蚁、结网、畋猎、余事勿取"
    },
    {
        "ID": 19876,
        "day": 2,
        "ji": "作灶、安床、开仓、造屋、动土、安葬",
        "month": 6,
        "year": 1955,
        "yi": "纳采、订盟、嫁娶、祭祀、祈福、求嗣、开光、解除、出行、出火、入宅、移徙、栽种、纳畜、牧养、动土、破土、入殓、安葬"
    },
    {
        "ID": 19877,
        "day": 3,
        "ji": "嫁娶、栽种、修造、动土、出行、伐木、作梁、安葬、谢土",
        "month": 6,
        "year": 1955,
        "yi": "开光、纳采、裁衣、冠笄、安床、作灶、进人口、造仓、塞穴"
    },
    {
        "ID": 19878,
        "day": 4,
        "ji": "伐木、安葬、安床、祭祀、祈福",
        "month": 6,
        "year": 1955,
        "yi": "纳采、嫁娶、裁衣、理发、出行、修造、动土、进人口、开市、交易、立券、挂匾、移徙、上梁、栽种、纳畜"
    },
    {
        "ID": 19879,
        "day": 5,
        "ji": "作灶、嫁娶、移徙、入宅、理发",
        "month": 6,
        "year": 1955,
        "yi": "开市、交易、立券、挂匾、祭祀、祈福、斋醮、出行、开市、交易、立券、造屋、起基、修造、动土、定磉、安床、安机械、安葬、破土、启攒、除服、成服、立碑"
    },
    {
        "ID": 19880,
        "day": 6,
        "ji": "作灶",
        "month": 6,
        "year": 1955,
        "yi": "嫁娶、订盟、纳采、出行、开市、祭祀、祈福、动土、移徙、入宅、破土、安葬"
    },
    {
        "ID": 19881,
        "day": 7,
        "ji": "开市、安葬",
        "month": 6,
        "year": 1955,
        "yi": "订盟、纳采、出行、祭祀、祈福、修造、动土、移徙、入宅"
    },
    {
        "ID": 19882,
        "day": 8,
        "ji": "诸事不宜",
        "month": 6,
        "year": 1955,
        "yi": "诸事不宜"
    },
    {
        "ID": 19883,
        "day": 9,
        "ji": "开光、开市",
        "month": 6,
        "year": 1955,
        "yi": "嫁娶、订盟、纳采、祭祀、祈福、入殓、破土、安葬"
    },
    {
        "ID": 19884,
        "day": 10,
        "ji": "嫁娶、开光",
        "month": 6,
        "year": 1955,
        "yi": "开光、求医、治病、动土、上梁、入殓、破土、安葬"
    },
    {
        "ID": 19885,
        "day": 11,
        "ji": "诸事不宜",
        "month": 6,
        "year": 1955,
        "yi": "祭祀、栽种、余事勿取"
    },
    {
        "ID": 19886,
        "day": 12,
        "ji": "安葬、开市、交易、立券",
        "month": 6,
        "year": 1955,
        "yi": "嫁娶、开光、祭祀、祈福、求嗣、出行、解除、伐木、入宅、移徙、安床、出火、拆卸、修造、上梁、栽种、移柩"
    },
    {
        "ID": 19887,
        "day": 13,
        "ji": "安葬、出行、祈福、栽种",
        "month": 6,
        "year": 1955,
        "yi": "求嗣、嫁娶、纳采、合帐、裁衣、冠笄、伐木、作梁、修造、动土、起基、竖柱、上梁、安门、作灶、筑堤、造畜椆栖"
    },
    {
        "ID": 19888,
        "day": 14,
        "ji": "诸事不宜",
        "month": 6,
        "year": 1955,
        "yi": "祭祀、解除、余事勿取"
    },
    {
        "ID": 19889,
        "day": 15,
        "ji": "安葬、行丧、伐木、作梁",
        "month": 6,
        "year": 1955,
        "yi": "嫁娶、祭祀、祈福、出火、开光、求嗣、出行、拆卸、开市、交易、立券、挂匾、入宅、移徙、安床、栽种、动土"
    },
    {
        "ID": 19890,
        "day": 16,
        "ji": "置产、安床",
        "month": 6,
        "year": 1955,
        "yi": "开光、求嗣、出行、解除、伐木、出火、拆卸、修造、上梁、起基、入宅、移徙、开市、交易、立券、栽种、牧养、入殓、安葬、除服、成服"
    },
    {
        "ID": 19891,
        "day": 17,
        "ji": "出行、安门、修造、嫁娶、上梁、入宅",
        "month": 6,
        "year": 1955,
        "yi": "祭祀、理发、修饰垣墙、平治道涂、沐浴、整手足甲、扫舍"
    },
    {
        "ID": 19892,
        "day": 18,
        "month": 6,
        "year": 1955,
        "yi": "嫁娶、祭祀、开光、祈福、求嗣、出行、出火、拆卸、动土、修造、进人口、入宅、移徙、安床、挂匾、交易、立券、栽种、纳畜、入殓、破土、启攒、安葬"
    },
    {
        "ID": 19893,
        "day": 19,
        "ji": "嫁娶、开市、交易、行丧、安葬、修坟",
        "month": 6,
        "year": 1955,
        "yi": "祭祀、祈福、求嗣、开光、出行、伐木、出火、拆卸、修造、动土、起基、安床、入宅、移徙"
    },
    {
        "ID": 19894,
        "day": 20,
        "ji": "诸事不宜",
        "month": 6,
        "year": 1955,
        "yi": "破屋、坏垣、余事勿取"
    },
    {
        "ID": 19895,
        "day": 21,
        "ji": "嫁娶、造桥、词讼、移徙、安门、作灶、栽种",
        "month": 6,
        "year": 1955,
        "yi": "开市、交易、立券、纳财、开池、作厕、结网、祭祀、修造、动土、安床、放水、经络、破土"
    },
    {
        "ID": 19896,
        "day": 22,
        "ji": "嫁娶、出火、伐木、祭祀、入宅、移徙、纳畜、探病",
        "month": 6,
        "year": 1955,
        "yi": "开市、交易、立券、纳财、栽种、安床、拆卸、修造、动土、上梁、入殓、安葬、破土、除服、成服"
    },
    {
        "ID": 19897,
        "day": 23,
        "ji": "诸事不宜",
        "month": 6,
        "year": 1955,
        "yi": "祭祀、作灶、余事勿取"
    },
    {
        "ID": 19898,
        "day": 24,
        "ji": "诸事不宜",
        "month": 6,
        "year": 1955,
        "yi": "解除、坏垣、余事勿取"
    },
    {
        "ID": 19899,
        "day": 25,
        "ji": "嫁娶、掘井、入宅、移徙、出火、出行、行丧、安葬、开光、理发、进人口",
        "month": 6,
        "year": 1955,
        "yi": "修造、动土、起基、安门、安床、栽种、筑堤、补垣、造畜椆栖"
    },
    {
        "ID": 19900,
        "day": 26,
        "ji": "斋醮、移徙、入宅、动土",
        "month": 6,
        "year": 1955,
        "yi": "祭祀、教牛马、断蚁、余事勿取"
    },
    {
        "ID": 19901,
        "day": 27,
        "ji": "行丧、安葬、破土、作灶、伐木、斋醮",
        "month": 6,
        "year": 1955,
        "yi": "纳采、订盟、嫁娶、祭祀、祈福、开市、纳财、立券、移徙、出行、修造、动土、起基、定磉、竖柱、拆卸、扫舍、放水、安香、安床、造船、开池、掘井、造畜椆栖、栽种"
    },
    {
        "ID": 19902,
        "day": 28,
        "ji": "纳采、订盟、安床、谢土、破土、动土",
        "month": 6,
        "year": 1955,
        "yi": "嫁娶、开光、祭祀、祈福、出行、解除、移徙、入宅、开市、纳财、起基、修造、竖柱、上梁、造屋、作灶、出火、安香、补垣、塞穴、拆卸、放水、扫舍、造仓、造船、栽种、安葬"
    },
    {
        "ID": 19903,
        "day": 29,
        "ji": "破土、出行、栽种",
        "month": 6,
        "year": 1955,
        "yi": "嫁娶、祭祀、理发、作灶、修饰垣墙、平治道涂、整手足甲、沐浴、冠笄"
    },
    {
        "ID": 19904,
        "day": 30,
        "ji": "动土、掘井、破土",
        "month": 6,
        "year": 1955,
        "yi": "嫁娶、纳采、订盟、祭祀、祈福、求嗣、开光、出火、出行、拆卸、修造、动土、进人口、入宅、移徙、安床、交易、立券、挂匾、纳财、入殓、安葬、启攒、除服、成服"
    },
    {
        "ID": 19905,
        "day": 1,
        "ji": "嫁娶、开市、安葬、启攒、行丧",
        "month": 7,
        "year": 1955,
        "yi": "畋猎、捕捉、结网、取渔、祭祀、沐浴、余事勿取"
    },
    {
        "ID": 19906,
        "day": 2,
        "ji": "移徙、入宅、开仓、出货财",
        "month": 7,
        "year": 1955,
        "yi": "祭祀、破屋、坏垣、余事勿取"
    },
    {
        "ID": 19907,
        "day": 3,
        "ji": "出火、入宅",
        "month": 7,
        "year": 1955,
        "yi": "祭祀、斋醮、塑绘、开光、出行、修造、动土、造畜椆栖、安床、放水、掘井、开池、作厕、结网、破土"
    },
    {
        "ID": 19908,
        "day": 4,
        "ji": "作灶、出火、祭祀、嫁娶、入宅",
        "month": 7,
        "year": 1955,
        "yi": "开市、交易、立券、挂匾、开光、解除、拆卸、动土、安床、修造、上梁、置产、栽种、破土、安葬"
    },
    {
        "ID": 19909,
        "day": 5,
        "ji": "入宅、出行、掘井、安葬",
        "month": 7,
        "year": 1955,
        "yi": "祭祀、结网、余事勿取"
    },
    {
        "ID": 19910,
        "day": 6,
        "ji": "行丧、置产、入宅、安葬",
        "month": 7,
        "year": 1955,
        "yi": "嫁娶、纳采、订盟、冠笄、造车器、祭祀、开光、祈福、求嗣、出行、解除、伐木、出火、入宅、拆卸、修造、动土、上梁、安床、栽种、破土"
    },
    {
        "ID": 19911,
        "day": 7,
        "ji": "安床、祈福、出行、安葬、行丧、开光",
        "month": 7,
        "year": 1955,
        "yi": "嫁娶、合帐、裁衣、冠笄、伐木、上梁、出火、拆卸、移徙、修造、动土、安门、纳财、筑堤、栽种、塞穴"
    },
    {
        "ID": 19912,
        "day": 8,
        "ji": "诸事不宜",
        "month": 7,
        "year": 1955,
        "yi": "补垣、塞穴、结网、入殓、除服、成服、移柩、安葬、启攒、余事勿取"
    },
    {
        "ID": 19913,
        "day": 9,
        "ji": "动土、安葬",
        "month": 7,
        "year": 1955,
        "yi": "嫁娶、纳采、出行、祭祀、祈福、解除、移徙、入宅"
    },
    {
        "ID": 19914,
        "day": 10,
        "ji": "开市、入宅",
        "month": 7,
        "year": 1955,
        "yi": "嫁娶、祭祀、祈福、斋醮、治病、破土、安葬"
    },
    {
        "ID": 19915,
        "day": 11,
        "ji": "祈福、动土、破土",
        "month": 7,
        "year": 1955,
        "yi": "嫁娶、出行、开市、安床、入殓、启攒、安葬"
    },
    {
        "ID": 19916,
        "day": 12,
        "ji": "开仓、出货财、置产、安葬、动土、破土、掘井、栽种",
        "month": 7,
        "year": 1955,
        "yi": "嫁娶、祭祀、裁衣、结网、冠笄、沐浴"
    },
    {
        "ID": 19917,
        "day": 13,
        "ji": "嫁娶、破土、置产、栽种、安葬、修坟、行丧",
        "month": 7,
        "year": 1955,
        "yi": "入宅、移徙、安床、开光、祈福、求嗣、进人口、开市、交易、立券、出火、拆卸、修造、动土"
    },
    {
        "ID": 19918,
        "day": 14,
        "ji": "嫁娶、入宅、移徙、作灶、开市、交易、安门、栽种",
        "month": 7,
        "year": 1955,
        "yi": "祭祀、解除、沐浴、整手足甲、入殓、移柩、破土、启攒、安葬"
    },
    {
        "ID": 19919,
        "day": 15,
        "ji": "诸事不宜",
        "month": 7,
        "year": 1955,
        "yi": "破屋、坏垣、余事勿取"
    },
    {
        "ID": 19920,
        "day": 16,
        "ji": "伐木、祭祀、纳畜、祭祀",
        "month": 7,
        "year": 1955,
        "yi": "嫁娶、开光、出行、理发、作梁、出火、拆卸、修造、开市、交易、立券、挂匾、动土、入宅、移徙、安床、栽种"
    },
    {
        "ID": 19921,
        "day": 17,
        "month": 7,
        "year": 1955,
        "yi": "嫁娶、开光、出行、祈福、求嗣、解除、拆卸、动土、修造、进人口、开市、交易、立券、挂匾、入宅、移徙、安床、栽种、纳畜、入殓、移柩、安葬"
    },
    {
        "ID": 19922,
        "day": 18,
        "ji": "安葬、经络、修坟、破土、开市、安床、启攒、立碑",
        "month": 7,
        "year": 1955,
        "yi": "祭祀、作灶、纳财、栽种、纳畜、进人口"
    },
    {
        "ID": 19923,
        "day": 19,
        "ji": "嫁娶、出行、安葬、入殓、入宅、作灶、冠笄、上梁",
        "month": 7,
        "year": 1955,
        "yi": "祭祀、祈福、求嗣、开光、开市、牧养、理发"
    },
    {
        "ID": 19924,
        "day": 20,
        "ji": "余事勿取",
        "month": 7,
        "year": 1955,
        "yi": "祭祀、入殓、破土、除服、成服、移柩、启攒、安葬、谢土、余事勿取"
    },
    {
        "ID": 19925,
        "day": 21,
        "ji": "嫁娶、作灶、安葬、动土、词讼、作梁、伐木、掘井、破土、移徙",
        "month": 7,
        "year": 1955,
        "yi": "祭祀、出行、交易、割蜜、造畜椆栖"
    },
    {
        "ID": 19926,
        "day": 22,
        "month": 7,
        "year": 1955,
        "yi": "嫁娶、祭祀、祈福、求嗣、开光、出火、拆卸、修造、动土、进人口、开市、交易、立券、挂匾、入宅、移徙、栽种、纳畜、入殓、启攒、除服、成服"
    },
    {
        "ID": 19927,
        "day": 23,
        "ji": "作灶、动土、上梁、栽种、入宅、移徙、修造、祈福",
        "month": 7,
        "year": 1955,
        "yi": "嫁娶、开光、解除、安床、牧养、理发、开市、入殓、启攒、移柩、安葬、扫舍"
    },
    {
        "ID": 19928,
        "day": 24,
        "ji": "诸事不宜",
        "month": 7,
        "year": 1955,
        "yi": "祭祀、解除、余事勿取"
    },
    {
        "ID": 19929,
        "day": 25,
        "ji": "嫁娶、栽种、行丧、理发、修坟、行丧、作灶",
        "month": 7,
        "year": 1955,
        "yi": "祭祀、祈福、求嗣、开光、伐木、出火、拆卸、入宅、安床、修造、动土、上梁、挂匾、纳畜"
    },
    {
        "ID": 19930,
        "day": 26,
        "ji": "嫁娶、开市、出火、作灶、置产、斋醮、入宅、移徙、安门",
        "month": 7,
        "year": 1955,
        "yi": "解除、祭祀、理发、入殓、安葬、破土"
    },
    {
        "ID": 19931,
        "day": 27,
        "ji": "诸事不宜",
        "month": 7,
        "year": 1955,
        "yi": "破屋、坏垣、余事勿取"
    },
    {
        "ID": 19932,
        "day": 28,
        "ji": "入宅、移徙、作灶、祭祀、谢土",
        "month": 7,
        "year": 1955,
        "yi": "开市、交易、立券、纳财、动土、开光、出行、嫁娶、纳采、订盟、出行、纳财、入学、开仓、出货财、纳畜、牧养、栽种、破土、启攒、安葬、立碑"
    },
    {
        "ID": 19933,
        "day": 29,
        "ji": "掘井、伐木、纳畜、合寿木",
        "month": 7,
        "year": 1955,
        "yi": "嫁娶、纳采、订盟、祭祀、祈福、求嗣、开光、出火、出行、拆卸、修造、动土、进人口、开市、交易、立券、挂匾、入宅、移徙、安床、栽种、入殓、破土、谢土、安葬"
    },
    {
        "ID": 19934,
        "day": 30,
        "ji": "开渠、造船、安床、安葬、破土、出行、修坟、掘井、开市、开生坟",
        "month": 7,
        "year": 1955,
        "yi": "祭祀、冠笄、作灶、交易、纳财、栽种、结网、纳畜、牧养、进人口"
    },
    {
        "ID": 19935,
        "day": 31,
        "ji": "移徙、栽种、出行、行丧、破土、安葬、词讼",
        "month": 7,
        "year": 1955,
        "yi": "嫁娶、纳采、订盟、祭祀、祈福、求嗣、纳采、裁衣、冠笄、开光、安床、作梁、修造、动土、作灶、起基、上梁、造屋、纳畜、牧养"
    },
    {
        "ID": 19936,
        "day": 1,
        "ji": "开光、治病、嫁娶、掘井、破土、安葬",
        "month": 8,
        "year": 1955,
        "yi": "经络、祭祀、沐浴、补垣、塞穴、除服、成服、移柩、入殓、启攒、立碑"
    },
    {
        "ID": 19937,
        "day": 2,
        "ji": "移徙、入宅、栽种、动土、破土、作灶、安葬、行丧、伐木、上梁",
        "month": 8,
        "year": 1955,
        "yi": "嫁娶、祭祀、出行、裁衣、冠笄、交易、雕刻、纳财、造畜椆栖、造车器、雕刻、教牛马"
    },
    {
        "ID": 19938,
        "day": 3,
        "ji": "开市、入宅、出行、安床、作灶",
        "month": 8,
        "year": 1955,
        "yi": "修造、动土、安机械、祭祀、沐浴、解除、拆卸、治病、作灶、造屋、起基、开池、扫舍、造畜椆栖、开生坟、合寿木、安葬、破土、启攒、移柩、入殓、立碑"
    },
    {
        "ID": 19939,
        "day": 4,
        "ji": "上梁、入宅、修造、动土、破土、祭祀、祈福、斋醮",
        "month": 8,
        "year": 1955,
        "yi": "嫁娶、纳采、订盟、造车器、开光、出行、拆卸、起基、安床、除服、成服、开市、交易、立券、栽种、牧养、入殓、移柩、启攒"
    },
    {
        "ID": 19940,
        "day": 5,
        "ji": "动土、破土、治病、开渠",
        "month": 8,
        "year": 1955,
        "yi": "祭祀、嫁娶、畋猎、结网"
    },
    {
        "ID": 19941,
        "day": 6,
        "ji": "嫁娶、作灶、出火、置产、嫁娶、入宅、安葬",
        "month": 8,
        "year": 1955,
        "yi": "纳采、订盟、会亲友、入学、祭祀、祈福、求嗣、开光、出行、解除、理发、动土、起基、开市、交易、立券、纳财、造仓、栽种、纳畜、牧养"
    },
    {
        "ID": 19942,
        "day": 7,
        "ji": "嫁娶、斋醮、开市、出火、入宅、移徙、出行、作灶、安门、伐木",
        "month": 8,
        "year": 1955,
        "yi": "祭祀、祈福、解除、整手足甲、安床、沐浴、入殓、移柩、破土、启攒、安葬、谢土"
    },
    {
        "ID": 19943,
        "day": 8,
        "ji": "嫁娶、入宅",
        "month": 8,
        "year": 1955,
        "yi": "捕捉、结网、入殓、破土、安葬"
    },
    {
        "ID": 19944,
        "day": 9,
        "ji": "诸事不宜",
        "month": 8,
        "year": 1955,
        "yi": "沐浴、治病、破屋、坏垣、余事勿取"
    },
    {
        "ID": 19945,
        "day": 10,
        "ji": "动土、破土",
        "month": 8,
        "year": 1955,
        "yi": "嫁娶、订盟、纳采、出行、开市、祭祀、祈福、移徙、入宅、启攒、安葬"
    },
    {
        "ID": 19946,
        "day": 11,
        "ji": "开光、针灸",
        "month": 8,
        "year": 1955,
        "yi": "嫁娶、订盟、纳采、祭祀、祈福、求医、治病、动土、移徙、入宅、破土、安葬"
    },
    {
        "ID": 19947,
        "day": 12,
        "ji": "动土、安葬",
        "month": 8,
        "year": 1955,
        "yi": "订盟、纳采、祭祀、祈福、安机械、作灶、纳畜"
    },
    {
        "ID": 19948,
        "day": 13,
        "ji": "入宅、作梁、安门、伐木、修造、上梁、入殓、造屋",
        "month": 8,
        "year": 1955,
        "yi": "嫁娶、祭祀、祈福、求嗣、出行、动土、安床、掘井、破土、启攒"
    },
    {
        "ID": 19949,
        "day": 14,
        "ji": "造屋、开光、理发、造船、掘井、作灶",
        "month": 8,
        "year": 1955,
        "yi": "嫁娶、祭祀、祈福、求嗣、出行、出火、拆卸、修造、移徙、动土、安床、入殓、破土、安葬、启攒"
    },
    {
        "ID": 19950,
        "day": 15,
        "ji": "破土、置产、掘井、动土、安床",
        "month": 8,
        "year": 1955,
        "yi": "祭祀、祈福、求嗣、开光、出行、解除、上梁、造屋、移徙、安门、纳财、牧养、纳畜、安葬、启攒、入殓"
    },
    {
        "ID": 19951,
        "day": 16,
        "ji": "嫁娶、会亲友、进人口、出行、入宅、移徙、赴任、作灶",
        "month": 8,
        "year": 1955,
        "yi": "祭祀、解除、沐浴、理发、整手足甲、入殓、移柩、破土、安葬、扫舍"
    },
    {
        "ID": 19952,
        "day": 17,
        "ji": "嫁娶、纳财、祈福、安葬、修造、开市、交易、立券、动土、上梁",
        "month": 8,
        "year": 1955,
        "yi": "塑绘、开光、进人口、纳畜、补垣、塞穴、栽种、牧养"
    },
    {
        "ID": 19953,
        "day": 18,
        "ji": "诸事不宜",
        "month": 8,
        "year": 1955,
        "yi": "祭祀、作灶、沐浴、修饰垣墙、平治道涂、余事勿取"
    },
    {
        "ID": 19954,
        "day": 19,
        "ji": "嫁娶、移徙",
        "month": 8,
        "year": 1955,
        "yi": "祭祀、求嗣、开光、出行、伐木、作梁、出火、解除、拆卸、进人口、修造、动土、起基、安床、栽种、纳畜、入殓、破土、安葬、除服、成服"
    },
    {
        "ID": 19955,
        "day": 20,
        "ji": "诸事不宜",
        "month": 8,
        "year": 1955,
        "yi": "祭祀、求医、捕捉、栽种、塞穴、入殓、破土、安葬、移柩、余事勿取"
    },
    {
        "ID": 19956,
        "day": 21,
        "ji": "诸事不宜",
        "month": 8,
        "year": 1955,
        "yi": "破屋、坏垣、余事勿取"
    },
    {
        "ID": 19957,
        "day": 22,
        "ji": "诸事不宜",
        "month": 8,
        "year": 1955,
        "yi": "祭祀、结网、入殓、移柩、启攒、安葬、移柩、除服、成服、合寿木、余事勿取"
    },
    {
        "ID": 19958,
        "day": 23,
        "ji": "栽种、作灶、针灸、出行",
        "month": 8,
        "year": 1955,
        "yi": "嫁娶、出火、拆卸、祭祀、祈福、开光、伐木、动土、开市、交易、立券、入宅、移徙、安床、纳畜、入殓、安葬"
    },
    {
        "ID": 19959,
        "day": 24,
        "ji": "动土、破土、理发、出行、入宅、分居、安香、出火",
        "month": 8,
        "year": 1955,
        "yi": "祭祀、开光、解除、移徙、裁衣、开市、立券、祈福、求嗣、进人口、交易、纳财、纳畜"
    },
    {
        "ID": 19960,
        "day": 25,
        "ji": "造屋、入殓、安葬、伐木、入宅、移徙、置产、纳畜",
        "month": 8,
        "year": 1955,
        "yi": "嫁娶、祭祀、祈福、求嗣、开光、出行、解除、安床、栽种、移柩、进人口、会亲友、除服、成服"
    },
    {
        "ID": 19961,
        "day": 26,
        "ji": "开光、出行、修造、上梁、入宅、安门、作灶、裁衣",
        "month": 8,
        "year": 1955,
        "yi": "祭祀、动土、筑堤、开池、会亲友、塞穴、入殓、移柩、破土、安葬"
    },
    {
        "ID": 19962,
        "day": 27,
        "ji": "安床、动土、安葬、开生坟、合寿木",
        "month": 8,
        "year": 1955,
        "yi": "祭祀、裁衣、安门、纳财、扫舍、出行、进人口、作灶、纳畜、造畜椆栖"
    },
    {
        "ID": 19963,
        "day": 28,
        "ji": "嫁娶、出行、进人口、作灶、入宅、移徙、栽种、赴任",
        "month": 8,
        "year": 1955,
        "yi": "祭祀、解除、拆卸、修造、动土、起基、上梁、安床、安门、开渠、开池、入殓、破土、启攒"
    },
    {
        "ID": 19964,
        "day": 29,
        "ji": "伐木、谢土、行丧、祭祀、作灶、动土、破土、安葬、祈福",
        "month": 8,
        "year": 1955,
        "yi": "纳采、订盟、开光、出行、解除、安香、出火、拆卸、入宅、移徙、修造、上梁、安床、栽种、纳畜、会亲友、安机械、经络"
    },
    {
        "ID": 19965,
        "day": 30,
        "ji": "嫁娶、词讼、治病、置产、作梁、祈福、安葬、栽种、伐木、安门",
        "month": 8,
        "year": 1955,
        "yi": "修饰垣墙、平治道涂、祭祀、沐浴、作灶"
    },
    {
        "ID": 19966,
        "day": 31,
        "ji": "斋醮、开市、开仓、作灶、造船",
        "month": 8,
        "year": 1955,
        "yi": "嫁娶、祭祀、祈福、求嗣、出火、出行、开光、解除、拆卸、修造、进人口、安香、交易、立券、入宅、移徙、安床、动土、破土、谢土、安葬、入殓、除服、成服"
    },
    {
        "ID": 19967,
        "day": 1,
        "ji": "嫁娶、入宅、开市、交易",
        "month": 9,
        "year": 1955,
        "yi": "破土、安葬、移柩、入殓、祭祀、捕捉、除服、成服、余事勿取"
    },
    {
        "ID": 19968,
        "day": 2,
        "ji": "祈福、纳采、订盟、嫁娶、入宅、安葬",
        "month": 9,
        "year": 1955,
        "yi": "破屋、坏垣、治病、余事勿取"
    },
    {
        "ID": 19969,
        "day": 3,
        "ji": "掘井、理发、作灶、动土、破土、开池",
        "month": 9,
        "year": 1955,
        "yi": "嫁娶、开光、祭祀、祈福、求嗣、安香、出火、解除、伐木、入宅、移徙、安床、开市、交易、立券、栽种、出火、出行、安葬"
    },
    {
        "ID": 19970,
        "day": 4,
        "ji": "入宅、嫁娶、掘井、牧养",
        "month": 9,
        "year": 1955,
        "yi": "安机械、纳采、订盟、祭祀、祈福、求嗣、开光、普渡、出行、出火、拆卸、修造、动土、进人口、开市、交易、立券、移徙、安床、栽种、上梁、纳畜、破土、移柩、安葬"
    },
    {
        "ID": 19971,
        "day": 5,
        "ji": "行丧、安葬、出行、作梁、纳畜、伐木、造桥",
        "month": 9,
        "year": 1955,
        "yi": "嫁娶、祭祀、祈福、求嗣、裁衣、冠笄、经络、修造、进人口、安床、动土、竖柱、上梁、移徙、交易、立券、栽种、会亲友"
    },
    {
        "ID": 19972,
        "day": 6,
        "ji": "入宅、上梁、入殓、造屋、探病、作灶、安门、安葬、纳畜、伐木",
        "month": 9,
        "year": 1955,
        "yi": "嫁娶、纳采、订盟、开光、祭祀、出行、理发、动土、安床、放水、开渠、栽种、进人口"
    },
    {
        "ID": 19973,
        "day": 7,
        "ji": "嫁娶、入宅、斋醮、开光、针灸、掘井",
        "month": 9,
        "year": 1955,
        "yi": "祭祀、出行、作梁、出火、拆卸、修造、动土、起基、安床、补垣、塞穴、入殓、破土、安葬、移柩、造畜椆栖"
    },
    {
        "ID": 19974,
        "day": 8,
        "ji": "安床、开光、开市、交易",
        "month": 9,
        "year": 1955,
        "yi": "祭祀、裁衣、冠笄、嫁娶、安机械、拆卸、动土、起基、移徙、入宅、入殓、启攒、安葬、造仓、经络"
    },
    {
        "ID": 19975,
        "day": 9,
        "ji": "动土、冠笄、移徙、入宅、开市、竖柱、上梁",
        "month": 9,
        "year": 1955,
        "yi": "祭祀、出行、成服、除服、沐浴、入殓"
    },
    {
        "ID": 19976,
        "day": 10,
        "ji": "诸事不宜",
        "month": 9,
        "year": 1955,
        "yi": "祭祀、沐浴、赴任、出行、余事勿取"
    },
    {
        "ID": 19977,
        "day": 11,
        "ji": "诸事不宜",
        "month": 9,
        "year": 1955,
        "yi": "诸事不宜"
    },
    {
        "ID": 19978,
        "day": 12,
        "ji": "嫁娶、移徙、入宅、开市",
        "month": 9,
        "year": 1955,
        "yi": "沐浴、入殓、移柩、除服、成服、破土、平治道涂"
    },
    {
        "ID": 19979,
        "day": 13,
        "month": 9,
        "year": 1955,
        "yi": "嫁娶、祭祀、祈福、求嗣、沐浴、出火、出行、拆卸、修造、动土、进人口、开市、交易、立券、入宅、移徙、安床、栽种、纳畜、入殓、安葬、启攒、除服、成服"
    },
    {
        "ID": 19980,
        "day": 14,
        "ji": "嫁娶、出行、安床、作灶、祭祀、入宅、移徙、出火、进人口、置产",
        "month": 9,
        "year": 1955,
        "yi": "开光、解除、起基、动土、拆卸、上梁、立碑、修坟、安葬、破土、启攒、移柩"
    },
    {
        "ID": 19981,
        "day": 15,
        "ji": "诸事不宜",
        "month": 9,
        "year": 1955,
        "yi": "破屋、坏垣、余事勿取"
    },
    {
        "ID": 19982,
        "day": 16,
        "month": 9,
        "year": 1955,
        "yi": "嫁娶、祈福、求嗣、出行、出火、拆卸、修造、动土、上梁、开光、进人口、开市、交易、立券、挂匾、安床、入宅、移徙、栽种、伐木、入殓、破土、除服、成服"
    },
    {
        "ID": 19983,
        "day": 17,
        "ji": "嫁娶、立碑、出行、伐木、安葬、行丧、移徙、纳畜",
        "month": 9,
        "year": 1955,
        "yi": "开市、交易、立券、挂匾、祭祀、开光、进人口、入宅、安床、出火、拆卸、修造、动土、栽种"
    },
    {
        "ID": 19984,
        "day": 18,
        "ji": "探病、开渠、安葬、伐木、作灶、入宅",
        "month": 9,
        "year": 1955,
        "yi": "祭祀、理发、会亲友、进人口、嫁娶、针灸、入殓、移柩"
    },
    {
        "ID": 19985,
        "day": 19,
        "ji": "余事勿取",
        "month": 9,
        "year": 1955,
        "yi": "祭祀、立碑、修坟、启攒、除服、成服、余事勿取"
    },
    {
        "ID": 19986,
        "day": 20,
        "ji": "掘井、祈福、安床、开市、入宅、挂匾、开光",
        "month": 9,
        "year": 1955,
        "yi": "嫁娶、出行、伐木、拆卸、修造、动土、移徙、安葬、破土、修坟、立碑"
    },
    {
        "ID": 19987,
        "day": 21,
        "ji": "诸事不宜",
        "month": 9,
        "year": 1955,
        "yi": "祭祀、出行、扫舍、余事勿取"
    },
    {
        "ID": 19988,
        "day": 22,
        "ji": "伐木、行丧、作灶、作梁、安葬",
        "month": 9,
        "year": 1955,
        "yi": "嫁娶、祭祀、塑绘、开光、出行、解除、理发、整手足甲、动土、安床、开池、放水、扫舍"
    },
    {
        "ID": 19989,
        "day": 23,
        "ji": "作灶、行丧、理发、乘船、嫁娶、安葬",
        "month": 9,
        "year": 1955,
        "yi": "开市、交易、立券、挂匾、开光、出行、入宅、移徙、安床、出火、上梁"
    },
    {
        "ID": 19990,
        "day": 24,
        "ji": "诸事不宜",
        "month": 9,
        "year": 1955,
        "yi": "祭祀、沐浴、修饰垣墙、平治道涂、余事勿取"
    },
    {
        "ID": 19991,
        "day": 25,
        "month": 9,
        "year": 1955,
        "yi": "嫁娶、祭祀、祈福、求嗣、开光、出行、出火、拆卸、修造、动土、进人口、入宅、移徙、安床、开市、交易、立券、挂匾、栽种、纳畜、入殓、安葬、除服、成服"
    },
    {
        "ID": 19992,
        "day": 26,
        "ji": "诸事不宜",
        "month": 9,
        "year": 1955,
        "yi": "解除、坏垣、余事勿取"
    },
    {
        "ID": 19993,
        "day": 27,
        "ji": "诸事不宜",
        "month": 9,
        "year": 1955,
        "yi": "祭祀、治病、破屋、坏垣、余事勿取"
    },
    {
        "ID": 19994,
        "day": 28,
        "ji": "开市、掘井、开渠、造桥、造船",
        "month": 9,
        "year": 1955,
        "yi": "嫁娶、纳采、订盟、祭祀、开光、出行、理发、作梁、出火、拆卸、修造、动土、进人口、入宅、移徙、安床、移徙、拆卸、挂匾、栽种、纳畜、破土、安葬、入殓、除服、成服"
    },
    {
        "ID": 19995,
        "day": 29,
        "ji": "嫁娶、破土、进人口、出行、入宅、移徙、出火、纳畜、词讼、安葬",
        "month": 9,
        "year": 1955,
        "yi": "开市、交易、立券、纳财、挂匾、栽种、祭祀、祈福、开光、拆卸、动土、安床"
    },
    {
        "ID": 19996,
        "day": 30,
        "ji": "开仓、出货财、伐木、纳畜、开市、上梁、造屋、破土、启攒、栽种",
        "month": 9,
        "year": 1955,
        "yi": "嫁娶、祭祀、理发、进人口、作灶、移柩、冠笄、会亲友"
    },
    {
        "ID": 19997,
        "day": 1,
        "ji": "开市、入宅、嫁娶、动土、破土、安葬",
        "month": 10,
        "year": 1955,
        "yi": "祭祀、修坟、除服、成服、启攒、移柩、余事勿取"
    },
    {
        "ID": 19998,
        "day": 2,
        "ji": "祈福、开光、开市、入宅、动土",
        "month": 10,
        "year": 1955,
        "yi": "嫁娶、冠笄、安机械、解除、纳畜、牧养、沐浴、伐木、架马、作梁、安门、扫舍、合寿木、安葬、启攒、立碑、修坟"
    },
    {
        "ID": 19999,
        "day": 3,
        "ji": "动土、破土、置产、掘井",
        "month": 10,
        "year": 1955,
        "yi": "祭祀、出行、沐浴、扫舍、安葬、余事勿取"
    },
    {
        "ID": 20000,
        "day": 4,
        "ji": "造庙、行丧、安葬、伐木、作灶、造船",
        "month": 10,
        "year": 1955,
        "yi": "嫁娶、纳采、祭祀、解除、出行、修造、动土、开市、上梁、安床、整手足甲、扫舍、求医、治病、起基、定磉、造屋、合脊"
    },
    {
        "ID": 20001,
        "day": 5,
        "ji": "斋醮、嫁娶、行丧、动土、作灶、安葬、破土",
        "month": 10,
        "year": 1955,
        "yi": "纳采、订盟、开市、交易、立券、挂匾、纳财、栽种、进人口、入宅、移徙、安床、开光、出火、拆卸、安门、修造"
    },
    {
        "ID": 20002,
        "day": 6,
        "ji": "嫁娶、入宅、安床、出行",
        "month": 10,
        "year": 1955,
        "yi": "祭祀、沐浴、修饰垣墙、平治道涂、余事勿取"
    },
    {
        "ID": 20003,
        "day": 7,
        "ji": "作灶、出火、进人口、开渠、入宅、移徙、祭祀",
        "month": 10,
        "year": 1955,
        "yi": "开光、祈福、求嗣、斋醮、修造、动土、纳财、造仓、作厕、栽种、牧养、会亲友"
    },
    {
        "ID": 20004,
        "day": 8,
        "ji": "出火、入宅、移徙、祈福、祭祀、安床、开市、嫁娶、探病",
        "month": 10,
        "year": 1955,
        "yi": "开光、解除、拆卸、修造、动土、竖柱、安门、牧养、安葬、修坟、破土、移柩"
    },
    {
        "ID": 20005,
        "day": 9,
        "ji": "开市、赴任",
        "month": 10,
        "year": 1955,
        "yi": "嫁娶、订盟、纳采、出行、祭祀、祈福、动土、移徙、入宅、破土、安葬"
    },
    {
        "ID": 20006,
        "day": 10,
        "ji": "余事勿取",
        "month": 10,
        "year": 1955,
        "yi": "祭祀、解除、破屋、坏垣、余事勿取"
    },
    {
        "ID": 20007,
        "day": 11,
        "ji": "祈福、安葬",
        "month": 10,
        "year": 1955,
        "yi": "订盟、纳采、会亲友、安机械、纳财、牧养"
    },
    {
        "ID": 20008,
        "day": 12,
        "ji": "斋醮、安门",
        "month": 10,
        "year": 1955,
        "yi": "嫁娶、订盟、纳采、出行、开市、祭祀、祈福、动土、移徙、入宅、破土、安葬"
    },
    {
        "ID": 20009,
        "day": 13,
        "ji": "诸事不宜",
        "month": 10,
        "year": 1955,
        "yi": "祭祀、塞穴、余事勿取"
    },
    {
        "ID": 20010,
        "day": 14,
        "ji": "嫁娶、作灶、修坟、安门、入宅、立碑、安葬、安床",
        "month": 10,
        "year": 1955,
        "yi": "祭祀、祈福、求嗣、开光、开市、出行、解除、动土、起基、置产、栽种"
    },
    {
        "ID": 20011,
        "day": 15,
        "ji": "嫁娶、开光、会亲友、掘井、安门、栽种",
        "month": 10,
        "year": 1955,
        "yi": "祭祀、解除、裁衣、理发、安床、作灶、造畜椆栖、放水、筑堤、补垣、塞穴、整手足甲、扫舍"
    },
    {
        "ID": 20012,
        "day": 16,
        "ji": "动土、伐木、作梁、行丧、安葬、开生坟",
        "month": 10,
        "year": 1955,
        "yi": "祭祀、出行、裁衣、冠笄、会亲友、造畜椆栖、嫁娶、竖柱、上梁、移徙、纳财、纳畜"
    },
    {
        "ID": 20013,
        "day": 17,
        "ji": "安葬、修坟、作灶、破土、造庙、动土、嫁娶、纳采",
        "month": 10,
        "year": 1955,
        "yi": "祭祀、祈福、求嗣、开光、出行、解除、移徙、伐木、安床、纳畜、出火、拆卸"
    },
    {
        "ID": 20014,
        "day": 18,
        "ji": "嫁娶、作灶、出火、出行、入宅、移徙、安床、祈福、上梁",
        "month": 10,
        "year": 1955,
        "yi": "开市、交易、立券、纳财、会亲友、开光、理发、入殓、移柩、安葬、启攒"
    },
    {
        "ID": 20015,
        "day": 19,
        "ji": "诸事不宜",
        "month": 10,
        "year": 1955,
        "yi": "造畜椆栖、平治道涂、余事勿取"
    },
    {
        "ID": 20016,
        "day": 20,
        "ji": "余事勿取",
        "month": 10,
        "year": 1955,
        "yi": "入殓、破土、安葬、启攒、除服、成服、余事勿取"
    },
    {
        "ID": 20017,
        "day": 21,
        "ji": "余事勿取",
        "month": 10,
        "year": 1955,
        "yi": "祭祀、入殓、移柩、开生坟、破土、启攒、安葬、除服、成服、余事勿取"
    },
    {
        "ID": 20018,
        "day": 22,
        "ji": "诸事不宜",
        "month": 10,
        "year": 1955,
        "yi": "祭祀、解除、破屋、坏垣、余事勿取"
    },
    {
        "ID": 20019,
        "day": 23,
        "ji": "上梁、作灶、伐木、出行、安葬、安门、理发",
        "month": 10,
        "year": 1955,
        "yi": "嫁娶、求嗣、纳采、进人口、纳财、结网、纳畜、牧养、会亲友"
    },
    {
        "ID": 20020,
        "day": 24,
        "ji": "纳畜、伐木、置产、作梁、行丧、安葬、修坟、立碑",
        "month": 10,
        "year": 1955,
        "yi": "嫁娶、祭祀、开市、开光、出行、入宅、移徙、出火、拆卸、修造、安床"
    },
    {
        "ID": 20021,
        "day": 25,
        "ji": "安葬、开市、修坟、立碑",
        "month": 10,
        "year": 1955,
        "yi": "嫁娶、祭祀、作灶、纳财"
    },
    {
        "ID": 20022,
        "day": 26,
        "ji": "安床、安葬",
        "month": 10,
        "year": 1955,
        "yi": "嫁娶、祭祀、祈福、求嗣、开光、出行、解除、出火、进人口、开市、交易、立券、挂匾、纳财、入宅、移徙、栽种、破土、谢土"
    },
    {
        "ID": 20023,
        "day": 27,
        "ji": "开光、栽种",
        "month": 10,
        "year": 1955,
        "yi": "嫁娶、祭祀、祈福、求嗣、动土、安床、扫舍、入殓、移柩、破土、启攒、安葬、作灶、整手足甲、补垣、除服、成服"
    },
    {
        "ID": 20024,
        "day": 28,
        "ji": "伐木、行丧、破土、嫁娶、安葬、开渠",
        "month": 10,
        "year": 1955,
        "yi": "祭祀、祈福、求嗣、开光、出行、解除、上梁、入宅、移徙、安床、安门、纳财、纳畜、造畜椆栖"
    },
    {
        "ID": 20025,
        "day": 29,
        "ji": "嫁娶、安葬、行丧、词讼、造桥、作灶、破土、动土",
        "month": 10,
        "year": 1955,
        "yi": "祭祀、开光、出行、解除、理发、伐木、出火、拆卸、上梁、合脊、安床、造畜椆栖"
    },
    {
        "ID": 20026,
        "day": 30,
        "ji": "开市、入宅、出行、嫁娶、修坟、祈福、动土、入宅、安门、谢土、上梁",
        "month": 10,
        "year": 1955,
        "yi": "纳采、订盟、会亲友、沐浴、理发、裁衣、冠笄、安床、除服、成服、启攒、移柩、安葬、会亲友、开生坟"
    },
    {
        "ID": 20027,
        "day": 31,
        "ji": "嫁娶、开市、交易、入宅、入学、安葬",
        "month": 10,
        "year": 1955,
        "yi": "解除、祭祀、修饰垣墙、平治道涂、造畜椆栖、余事勿取"
    },
    {
        "ID": 20028,
        "day": 1,
        "ji": "开市、入宅、祭祀、置产、补垣、塞穴",
        "month": 11,
        "year": 1955,
        "yi": "入殓、破土、启攒、安葬、除服、成服、余事勿取"
    },
    {
        "ID": 20029,
        "day": 2,
        "ji": "入宅、移徙、掘井、理发、伐木、交易、开市、作灶",
        "month": 11,
        "year": 1955,
        "yi": "嫁娶、祭祀、祈福、求嗣、开光、出行、拆卸、修造、动土、上梁、安床、纳畜、入殓、破土"
    },
    {
        "ID": 20030,
        "day": 3,
        "ji": "嫁娶、入宅、上梁、出行、安葬",
        "month": 11,
        "year": 1955,
        "yi": "祭祀、沐浴、破屋、坏垣、余事勿取"
    },
    {
        "ID": 20031,
        "day": 4,
        "ji": "祈福、斋醮、纳采、订盟、嫁娶、入宅、安葬",
        "month": 11,
        "year": 1955,
        "yi": "祭祀、求嗣、冠笄、进人口、会亲友、安门、安床、经络、纳财、牧养、畋猎、放水、割蜜"
    },
    {
        "ID": 20032,
        "day": 5,
        "ji": "探病、纳畜、伐木、起基、作梁、造屋",
        "month": 11,
        "year": 1955,
        "yi": "嫁娶、纳采、订盟、开市、交易、立券、挂匾、祭祀、祈福、开光、造车器、挂匾、出行、入宅、移徙、安床、安门、拆卸、修造、动土、栽种、安葬、破土、启攒、除服、成服、入殓、立碑"
    },
    {
        "ID": 20033,
        "day": 6,
        "ji": "嫁娶、开市、开池、作厕、破土",
        "month": 11,
        "year": 1955,
        "yi": "祭祀、冠笄、移徙、会亲友、纳财、理发、捕捉"
    },
    {
        "ID": 20034,
        "day": 7,
        "ji": "安门、安床、裁衣、入宅、安葬",
        "month": 11,
        "year": 1955,
        "yi": "祭祀、祈福、求嗣、斋醮、开光、出行、嫁娶、求医、治病、动土、破土、入学、起基、扫舍、竖柱、上梁、开仓、出货财、置产、栽种、牧养、开生坟、谢土、立碑"
    },
    {
        "ID": 20035,
        "day": 8,
        "ji": "诸事不宜",
        "month": 11,
        "year": 1955,
        "yi": "诸事不宜"
    },
    {
        "ID": 20036,
        "day": 9,
        "ji": "入宅、作灶",
        "month": 11,
        "year": 1955,
        "yi": "祈福、斋醮、出行、订盟、纳采、入殓、移柩、破土、安葬、立碑、结网"
    },
    {
        "ID": 20037,
        "day": 10,
        "ji": "嫁娶、动土、安葬、作灶",
        "month": 11,
        "year": 1955,
        "yi": "祭祀、沐浴、出行、冠笄、进人口、余事勿取"
    },
    {
        "ID": 20038,
        "day": 11,
        "ji": "开市",
        "month": 11,
        "year": 1955,
        "yi": "祭祀、祈福、斋醮、塑绘、开光、订盟、纳采、裁衣、冠笄、嫁娶、拆卸、入宅、安香、入殓、移柩、理发、安葬、修坟、谢土、赴任、移徙、沐浴、治病、破土、启攒、整手足甲、入学、作梁"
    },
    {
        "ID": 20039,
        "day": 12,
        "ji": "诸事不宜",
        "month": 11,
        "year": 1955,
        "yi": "诸事不宜"
    },
    {
        "ID": 20040,
        "day": 13,
        "ji": "栽种、破土、置产、祭祀、嫁娶、动土、作灶、祈福",
        "month": 11,
        "year": 1955,
        "yi": "开市、交易、立券、挂匾、纳财、开光、出行、入宅、移徙、安床、纳畜、入殓、移柩、安葬"
    },
    {
        "ID": 20041,
        "day": 14,
        "month": 11,
        "year": 1955,
        "yi": "嫁娶、祭祀、祈福、求嗣、开光、出行、解除、出火、出行、拆卸、进人口、入宅、移徙、安床、栽种、动土、修造、纳畜、入殓、安葬、立碑、除服、成服"
    },
    {
        "ID": 20042,
        "day": 15,
        "ji": "嫁娶、开市、出火、栽种、破土、动土、入宅、移徙、安香、分居、掘井、作灶",
        "month": 11,
        "year": 1955,
        "yi": "开光、解除、拆卸、修造、动土、安床、纳畜、安葬、启攒、入殓"
    },
    {
        "ID": 20043,
        "day": 16,
        "ji": "诸事不宜",
        "month": 11,
        "year": 1955,
        "yi": "破屋、坏垣、余事勿取"
    },
    {
        "ID": 20044,
        "day": 17,
        "ji": "探病、安葬",
        "month": 11,
        "year": 1955,
        "yi": "嫁娶、祭祀、开光、出火、出行、拆卸、修造、动土、解除、开市、交易、立券、挂匾、纳财、入宅、移徙、安床、栽种、纳畜"
    },
    {
        "ID": 20045,
        "day": 18,
        "ji": "入宅、作灶、词讼、移徙、出行、赴任",
        "month": 11,
        "year": 1955,
        "yi": "祭祀、祈福、求嗣、开光、解除、理发、会亲友、栽种、纳畜、牧养、安葬、修坟、立碑、启攒"
    },
    {
        "ID": 20046,
        "day": 19,
        "ji": "安床、开市、交易、出货财、安葬、修坟、嫁娶、作灶",
        "month": 11,
        "year": 1955,
        "yi": "祭祀、沐浴、结网、移柩、入殓、除服、成服"
    },
    {
        "ID": 20047,
        "day": 20,
        "ji": "余事勿取",
        "month": 11,
        "year": 1955,
        "yi": "解除、余事勿取"
    },
    {
        "ID": 20048,
        "day": 21,
        "ji": "入宅、移徙、嫁娶、掘井、作灶、出火、进人口、开市、开光",
        "month": 11,
        "year": 1955,
        "yi": "安床、祭祀、开池、补垣、入殓、移柩、破土、启攒"
    },
    {
        "ID": 20049,
        "day": 22,
        "ji": "余事勿取",
        "month": 11,
        "year": 1955,
        "yi": "祭祀、沐浴、余事勿取"
    },
    {
        "ID": 20050,
        "day": 23,
        "ji": "置产、安床",
        "month": 11,
        "year": 1955,
        "yi": "嫁娶、开光、出行、解除、出火、拆卸、修造、进人口、动土、入宅、移徙、栽种、纳畜、掘井、安葬、除服、成服"
    },
    {
        "ID": 20051,
        "day": 24,
        "ji": "嫁娶、冠笄、出行、祈福、安葬、伐木、入宅、移徙、出火、栽种、动土、上梁",
        "month": 11,
        "year": 1955,
        "yi": "开光、裁衣、安门、会亲友、安床、结网、理发"
    },
    {
        "ID": 20052,
        "day": 25,
        "ji": "祈福、祭祀、伐木、掘井、作灶、谢土",
        "month": 11,
        "year": 1955,
        "yi": "嫁娶、开光、出行、出火、拆卸、修造、动土、入宅、移徙、安床、上梁、开市、交易、立券、栽种"
    },
    {
        "ID": 20053,
        "day": 26,
        "ji": "栽种、掘井、置产",
        "month": 11,
        "year": 1955,
        "yi": "嫁娶、祭祀、祈福、求嗣、开光、出火、出行、拆卸、开市、交易、立券、挂匾、伐木、入宅、移徙、安床、安葬"
    },
    {
        "ID": 20054,
        "day": 27,
        "ji": "嫁娶、动土、造船、开池、掘井、出行、修造、入宅、上梁、移徙、安葬、破土、作灶、开市",
        "month": 11,
        "year": 1955,
        "yi": "祭祀、理发、针灸、解除、进人口、整手足甲"
    },
    {
        "ID": 20055,
        "day": 28,
        "ji": "嫁娶、安葬",
        "month": 11,
        "year": 1955,
        "yi": "破屋、坏垣、求医、治病、余事勿取"
    },
    {
        "ID": 20056,
        "day": 29,
        "ji": "上梁、开仓、出货财、造屋、造船",
        "month": 11,
        "year": 1955,
        "yi": "纳采、订盟、嫁娶、祭祀、祈福、雕刻、移徙、开市、入宅、出行、动土、会亲友、入学、修造、动土、起基、安门、安床、造庙、解除、纳财、开池、造畜椆栖、牧养、牧养"
    },
    {
        "ID": 20057,
        "day": 30,
        "ji": "嫁娶、进人口、入宅、移徙、出火、出行",
        "month": 11,
        "year": 1955,
        "yi": "祭祀、祈福、求嗣、开光、解除、伐木、拆卸、修造、栽种、纳畜、安葬、修坟、立碑"
    },
    {
        "ID": 20058,
        "day": 1,
        "ji": "嫁娶、入宅、开市、安床、破土、修坟",
        "month": 12,
        "year": 1955,
        "yi": "沐浴、扫舍、捕捉、畋猎、解除、塞穴、余事勿取"
    },
    {
        "ID": 20059,
        "day": 2,
        "ji": "伐木、上梁、修造、入殓、理发、会亲友、入宅、安门、安葬、作灶",
        "month": 12,
        "year": 1955,
        "yi": "嫁娶、冠笄、祭祀、祈福、求嗣、斋醮、开光、出行、解除、动土、开市、交易、立券、挂匾、拆卸、破土"
    },
    {
        "ID": 20060,
        "day": 3,
        "ji": "置产、造船、开光、掘井、作灶",
        "month": 12,
        "year": 1955,
        "yi": "合帐、裁衣、嫁娶、安床、入殓、移柩、破土、造畜椆栖"
    },
    {
        "ID": 20061,
        "day": 4,
        "ji": "开市、动土、破土、嫁娶、安葬",
        "month": 12,
        "year": 1955,
        "yi": "解除、修饰垣墙、冠笄、出行、余事勿取"
    },
    {
        "ID": 20062,
        "day": 5,
        "ji": "作灶、经络、安床",
        "month": 12,
        "year": 1955,
        "yi": "纳采、订盟、嫁娶、祭祀、祈福、求嗣、开光、出行、解除、进人口、开市、立券、挂匾、入宅、移徙、安门、栽种、动土、求医、治病、会亲友、起基、修造、造屋、安葬"
    },
    {
        "ID": 20063,
        "day": 6,
        "ji": "祈福、谢土、安葬、上梁、作灶、开市、嫁娶、出行、入宅、动土",
        "month": 12,
        "year": 1955,
        "yi": "祭祀、塑绘、理发、会亲友、牧养、开池、造畜椆栖、畋猎、结网"
    },
    {
        "ID": 20064,
        "day": 7,
        "ji": "造庙、谢土、作灶、作梁、伐木、安葬、行丧、修坟、探病",
        "month": 12,
        "year": 1955,
        "yi": "出行、纳财、开市、交易、立券、动土、移徙、入宅、裁衣、会亲友、拆卸、进人口、安香、经络、出货财、修饰垣墙、平治道涂"
    },
    {
        "ID": 20065,
        "day": 8,
        "ji": "诸事不宜",
        "month": 12,
        "year": 1955,
        "yi": "平治道涂、余事勿取"
    },
    {
        "ID": 20066,
        "day": 9,
        "ji": "开市、嫁娶",
        "month": 12,
        "year": 1955,
        "yi": "求嗣、斋醮、塑绘、订盟、纳采、出火、拆卸、修造、动土、造桥、安机械、栽种、纳畜、牧养、入殓、除服、成服、移柩、破土、安葬"
    },
    {
        "ID": 20067,
        "day": 10,
        "ji": "开市、安葬",
        "month": 12,
        "year": 1955,
        "yi": "嫁娶、订盟、纳采、祭祀、祈福、修造、动土、移徙、入宅"
    },
    {
        "ID": 20068,
        "day": 11,
        "ji": "诸事不宜",
        "month": 12,
        "year": 1955,
        "yi": "治病、破屋、坏垣、余事勿取"
    },
    {
        "ID": 20069,
        "day": 12,
        "ji": "造桥、安门、理发、造庙、栽种、作灶",
        "month": 12,
        "year": 1955,
        "yi": "祭祀、祈福、求嗣、斋醮、开光、入学、订盟、冠笄、伐木、修造、动土、起基、放水、交易、开池"
    },
    {
        "ID": 20070,
        "day": 13,
        "ji": "诸事不宜",
        "month": 12,
        "year": 1955,
        "yi": "解除、坏垣、余事勿取"
    },
    {
        "ID": 20071,
        "day": 14,
        "ji": "伐木、纳畜、上梁、入宅、作灶、造畜椆栖、嫁娶、安葬、作梁、造船、安门",
        "month": 12,
        "year": 1955,
        "yi": "沐浴、理发、扫舍"
    },
    {
        "ID": 20072,
        "day": 15,
        "ji": "嫁娶、出行、赴任、造屋、入殓、入宅、移徙、出火、进人口、安葬",
        "month": 12,
        "year": 1955,
        "yi": "祭祀、开光、祈福、解除、作梁、动土、安床、掘井、栽种、纳畜、破土、移柩"
    },
    {
        "ID": 20073,
        "day": 16,
        "ji": "嫁娶、祈福、掘井、行丧、安葬、安床",
        "month": 12,
        "year": 1955,
        "yi": "诸事不宜、作梁、修造、动土、安门、作灶、塞穴、开池、作厕、筑堤、补垣、栽种"
    },
    {
        "ID": 20074,
        "day": 17,
        "ji": "余事勿取",
        "month": 12,
        "year": 1955,
        "yi": "安葬、启攒、移柩、入殓、除服、成服"
    },
    {
        "ID": 20075,
        "day": 18,
        "ji": "作灶、塑绘、行丧、词讼、伐木、安葬",
        "month": 12,
        "year": 1955,
        "yi": "嫁娶、祭祀、祈福、求嗣、出行、出火、拆卸、开市、交易、立券、挂匾、入宅、移徙、安床、栽种"
    },
    {
        "ID": 20076,
        "day": 19,
        "ji": "入宅、移徙、作灶、祈福、祭祀、嫁娶、谢土、掘井、造屋、探病",
        "month": 12,
        "year": 1955,
        "yi": "理发、开光、解除、拆卸、修造、安葬、开市、交易、立券、挂匾、安床、栽种"
    },
    {
        "ID": 20077,
        "day": 20,
        "ji": "诸事不宜",
        "month": 12,
        "year": 1955,
        "yi": "祭祀、修饰垣墙、余事勿取"
    },
    {
        "ID": 20078,
        "day": 21,
        "ji": "嫁娶、开市、作灶、置产、作梁、伐木",
        "month": 12,
        "year": 1955,
        "yi": "入宅、安床、开光、祭祀、出火、拆卸、动土、挂匾、入殓、破土、安葬、纳畜"
    },
    {
        "ID": 20079,
        "day": 22,
        "ji": "诸事不宜",
        "month": 12,
        "year": 1955,
        "yi": "祭祀、解除、余事勿取"
    },
    {
        "ID": 20080,
        "day": 23,
        "ji": "诸事不宜",
        "month": 12,
        "year": 1955,
        "yi": "破屋、坏垣、祭祀、沐浴、余事勿取"
    },
    {
        "ID": 20081,
        "day": 24,
        "ji": "安门、栽种、作灶、治病",
        "month": 12,
        "year": 1955,
        "yi": "安床、祭祀、祈福、求嗣、冠笄、伐木、架马、动土、开池、作厕、结网、入殓、除服、成服"
    },
    {
        "ID": 20082,
        "day": 25,
        "ji": "诸事不宜",
        "month": 12,
        "year": 1955,
        "yi": "解除、扫舍、余事勿取"
    },
    {
        "ID": 20083,
        "day": 26,
        "ji": "伐木、纳畜、破土、安葬、开生坟、嫁娶、开市、动土、交易、作梁",
        "month": 12,
        "year": 1955,
        "yi": "祭祀、开光、理发、整手足甲、安床、作灶、扫舍、教牛马"
    },
    {
        "ID": 20084,
        "day": 27,
        "ji": "嫁娶、进人口、安葬、出行、赴任、入宅、移徙、入殓、开渠",
        "month": 12,
        "year": 1955,
        "yi": "祭祀、祈福、求嗣、开光、拆卸、修造、动土、上梁、安床、置产、栽种、破土"
    },
    {
        "ID": 20085,
        "day": 28,
        "ji": "移徙、入宅、嫁娶、祈福、开光、掘井",
        "month": 12,
        "year": 1955,
        "yi": "沐浴、冠笄、补垣、塞穴、合帐、裁衣、修造、作梁、开柱眼、安碓磑、筑堤、作厕、断蚁"
    },
    {
        "ID": 20086,
        "day": 29,
        "ji": "斋醮、入宅、修造、动土、破土",
        "month": 12,
        "year": 1955,
        "yi": "交易、进人口、祭祀、沐浴、捕捉、入殓、除服、成服、安葬、谢土、启攒、修坟"
    },
    {
        "ID": 20087,
        "day": 30,
        "ji": "斋醮、伐木、作梁、安葬、行丧",
        "month": 12,
        "year": 1955,
        "yi": "嫁娶、纳采、订盟、造车器、祭祀、祈福、造庙、安香、出火、出行、归宁、入学、入宅、交易、立券、求医、治病、修造、动土、竖柱、上梁、造屋、起基、安门"
    },
    {
        "ID": 20088,
        "day": 31,
        "ji": "嫁娶、动土、破土、祈福、出火、入宅",
        "month": 12,
        "year": 1955,
        "yi": "纳采、订盟、开市、交易、立券、出行、会亲友、安机械、竖柱、上梁、平治道涂、伐木、拆卸、造屋、起基、安床、安门、解除、安葬、启攒、除服、成服、修坟、立碑、移柩、入殓"
    }
]
